{
  "match_info": {
    "team1": "Kolkata Knight Riders",
    "team2": "Mumbai Indians",
    "venue": "Wankhede Stadium, Mumbai",
    "date": "2026-03-29",
    "toss_winner": "Mumbai Indians",
    "toss_decision": "field",
    "result": "MI won by 6 wickets (with 5 balls remaining)",
    "winner": "Mumbai Indians",
    "margin": "6 wickets",
    "player_of_match": "Shardul Thakur",
    "team1_impact_player_in": "Kartik Tyagi",
    "team1_impact_player_out": "Finn Allen",
    "team1_impact_player_over": 20,
    "team2_impact_player_in": "Suryakumar Yadav",
    "team2_impact_player_out": "Jasprit Bumrah",
    "team2_impact_player_over": 12
  },
  "refined_critechery_score": {
    "kkr": {
      "total": 52.4,
      "batting": {
        "sr_dominance": {
          "value": 16.7,
          "max": 25
        },
        "boundary_efficiency": {
          "value": 15,
          "max": 15
        },
        "extras_discipline": {
          "value": 0,
          "max": 10
        },
        "batting_total": 31.7
      },
      "bowling": {
        "economy_squeeze": {
          "value": 0,
          "max": 15
        },
        "wicket_punch": {
          "value": 7.5,
          "max": 15
        },
        "dot_dominance": {
          "value": 10,
          "max": 10
        },
        "bowling_strike_rate": {
          "value": 3.1,
          "max": 10
        },
        "bowling_total": 20.6
      },
      "_debug": {
        "weighted_sr": 173.6,
        "team_economy": 11.62,
        "total_wickets": 3,
        "dot_pct": 30.4
      }
    },
    "mi": {
      "total": 60.9,
      "batting": {
        "sr_dominance": {
          "value": 21.2,
          "max": 25
        },
        "boundary_efficiency": {
          "value": 15,
          "max": 15
        },
        "extras_discipline": {
          "value": 1.0,
          "max": 10
        },
        "batting_total": 37.2
      },
      "bowling": {
        "economy_squeeze": {
          "value": 0.3,
          "max": 15
        },
        "wicket_punch": {
          "value": 10.0,
          "max": 15
        },
        "dot_dominance": {
          "value": 9.3,
          "max": 10
        },
        "bowling_strike_rate": {
          "value": 4.0,
          "max": 10
        },
        "bowling_total": 23.6
      },
      "_debug": {
        "weighted_sr": 187.9,
        "team_economy": 10.9,
        "total_wickets": 4,
        "dot_pct": 26.7
      }
    }
  },
  "humdinger_score": {
    "score": 4.1,
    "components": {
      "time_near_50_pct": 10.4,
      "score_a_win_prob_closeness": 2.1,
      "score_b_last_over_drama": 2.0,
      "score_c_margin": 0.0,
      "score_d_wicket_cluster": 0.0,
      "score_e_boundary_burst": 0.0
    },
    "debug": {
      "kkr_death_boundary_pct": 20.8,
      "mi_death_boundary_pct": 26.3,
      "mi_wicket_cluster_found": false
    }
  },
  "pressure_index": {
    "innings1": [
      {
        "over": 0,
        "pressure": 0.267,
        "dot_pct": 66.7,
        "wickets": 0,
        "runs": 8,
        "actual_rr": 8.0,
        "flag": "above_average"
      },
      {
        "over": 1,
        "pressure": 0.453,
        "dot_pct": 83.3,
        "wickets": 0,
        "runs": 4,
        "actual_rr": 4.0,
        "flag": "high"
      },
      {
        "over": 2,
        "pressure": 0.403,
        "dot_pct": 33.3,
        "wickets": 0,
        "runs": 17,
        "actual_rr": 17.0,
        "flag": "high"
      },
      {
        "over": 3,
        "pressure": 0.547,
        "dot_pct": 16.7,
        "wickets": 0,
        "runs": 24,
        "actual_rr": 24.0,
        "flag": "extreme"
      },
      {
        "over": 4,
        "pressure": 0.157,
        "dot_pct": 16.7,
        "wickets": 0,
        "runs": 11,
        "actual_rr": 11.0,
        "flag": "normal"
      },
      {
        "over": 5,
        "pressure": 0.427,
        "dot_pct": 16.7,
        "wickets": 1,
        "runs": 10,
        "actual_rr": 10.0,
        "flag": "high"
      },
      {
        "over": 6,
        "pressure": 0.307,
        "dot_pct": 16.7,
        "wickets": 0,
        "runs": 16,
        "actual_rr": 16.0,
        "flag": "above_average"
      },
      {
        "over": 7,
        "pressure": 0.06,
        "dot_pct": 0.0,
        "wickets": 0,
        "runs": 6,
        "actual_rr": 6.0,
        "flag": "normal"
      },
      {
        "over": 8,
        "pressure": 0.33,
        "dot_pct": 0.0,
        "wickets": 1,
        "runs": 9,
        "actual_rr": 9.0,
        "flag": "above_average"
      },
      {
        "over": 9,
        "pressure": 0.06,
        "dot_pct": 0.0,
        "wickets": 0,
        "runs": 10,
        "actual_rr": 10.0,
        "flag": "normal"
      },
      {
        "over": 10,
        "pressure": 0.26,
        "dot_pct": 50.0,
        "wickets": 0,
        "runs": 10,
        "actual_rr": 10.0,
        "flag": "normal"
      },
      {
        "over": 11,
        "pressure": 0.157,
        "dot_pct": 16.7,
        "wickets": 0,
        "runs": 5,
        "actual_rr": 5.0,
        "flag": "normal"
      },
      {
        "over": 12,
        "pressure": 0.133,
        "dot_pct": 33.3,
        "wickets": 0,
        "runs": 8,
        "actual_rr": 8.0,
        "flag": "normal"
      },
      {
        "over": 13,
        "pressure": 0.493,
        "dot_pct": 33.3,
        "wickets": 1,
        "runs": 6,
        "actual_rr": 6.0,
        "flag": "extreme"
      },
      {
        "over": 14,
        "pressure": 0.337,
        "dot_pct": 16.7,
        "wickets": 0,
        "runs": 17,
        "actual_rr": 17.0,
        "flag": "above_average"
      },
      {
        "over": 15,
        "pressure": 0.097,
        "dot_pct": 16.7,
        "wickets": 0,
        "runs": 9,
        "actual_rr": 9.0,
        "flag": "normal"
      },
      {
        "over": 16,
        "pressure": 0.247,
        "dot_pct": 16.7,
        "wickets": 0,
        "runs": 14,
        "actual_rr": 14.0,
        "flag": "normal"
      },
      {
        "over": 17,
        "pressure": 0.067,
        "dot_pct": 16.7,
        "wickets": 0,
        "runs": 8,
        "actual_rr": 8.0,
        "flag": "normal"
      },
      {
        "over": 18,
        "pressure": 0.33,
        "dot_pct": 0.0,
        "wickets": 1,
        "runs": 9,
        "actual_rr": 9.0,
        "flag": "above_average"
      },
      {
        "over": 19,
        "pressure": 0.097,
        "dot_pct": 16.7,
        "wickets": 0,
        "runs": 9,
        "actual_rr": 9.0,
        "flag": "normal"
      }
    ],
    "innings2": [
      {
        "over": 0,
        "pressure": 0.357,
        "dot_pct": 66.7,
        "wickets": 0,
        "runs": 5,
        "actual_rr": 5.0,
        "flag": "above_average"
      },
      {
        "over": 1,
        "pressure": 0.23,
        "dot_pct": 50.0,
        "wickets": 0,
        "runs": 9,
        "actual_rr": 9.0,
        "flag": "normal"
      },
      {
        "over": 2,
        "pressure": 0.463,
        "dot_pct": 33.3,
        "wickets": 0,
        "runs": 19,
        "actual_rr": 19.0,
        "flag": "high"
      },
      {
        "over": 3,
        "pressure": 0.277,
        "dot_pct": 16.7,
        "wickets": 0,
        "runs": 15,
        "actual_rr": 15.0,
        "flag": "normal"
      },
      {
        "over": 4,
        "pressure": 0.343,
        "dot_pct": 33.3,
        "wickets": 0,
        "runs": 15,
        "actual_rr": 15.0,
        "flag": "above_average"
      },
      {
        "over": 5,
        "pressure": 0.373,
        "dot_pct": 33.3,
        "wickets": 0,
        "runs": 16,
        "actual_rr": 16.0,
        "flag": "above_average"
      },
      {
        "over": 6,
        "pressure": 0.2,
        "dot_pct": 50.0,
        "wickets": 0,
        "runs": 8,
        "actual_rr": 8.0,
        "flag": "normal"
      },
      {
        "over": 7,
        "pressure": 0.067,
        "dot_pct": 16.7,
        "wickets": 0,
        "runs": 8,
        "actual_rr": 8.0,
        "flag": "normal"
      },
      {
        "over": 8,
        "pressure": 0.313,
        "dot_pct": 33.3,
        "wickets": 0,
        "runs": 14,
        "actual_rr": 14.0,
        "flag": "above_average"
      },
      {
        "over": 9,
        "pressure": 0.127,
        "dot_pct": 16.7,
        "wickets": 0,
        "runs": 10,
        "actual_rr": 10.0,
        "flag": "normal"
      },
      {
        "over": 10,
        "pressure": 0.217,
        "dot_pct": 16.7,
        "wickets": 0,
        "runs": 13,
        "actual_rr": 13.0,
        "flag": "normal"
      },
      {
        "over": 11,
        "pressure": 0.54,
        "dot_pct": 0.0,
        "wickets": 1,
        "runs": 16,
        "actual_rr": 16.0,
        "flag": "extreme"
      },
      {
        "over": 12,
        "pressure": 0.127,
        "dot_pct": 16.7,
        "wickets": 0,
        "runs": 10,
        "actual_rr": 10.0,
        "flag": "normal"
      },
      {
        "over": 13,
        "pressure": 0.157,
        "dot_pct": 16.7,
        "wickets": 0,
        "runs": 11,
        "actual_rr": 11.0,
        "flag": "normal"
      },
      {
        "over": 14,
        "pressure": 0.5,
        "dot_pct": 50.0,
        "wickets": 1,
        "runs": 8,
        "actual_rr": 8.0,
        "flag": "extreme"
      },
      {
        "over": 15,
        "pressure": 0.463,
        "dot_pct": 33.3,
        "wickets": 1,
        "runs": 9,
        "actual_rr": 9.0,
        "flag": "high"
      },
      {
        "over": 16,
        "pressure": 0.163,
        "dot_pct": 33.3,
        "wickets": 0,
        "runs": 7,
        "actual_rr": 7.0,
        "flag": "normal"
      },
      {
        "over": 17,
        "pressure": 0.157,
        "dot_pct": 16.7,
        "wickets": 0,
        "runs": 11,
        "actual_rr": 11.0,
        "flag": "normal"
      },
      {
        "over": 18,
        "pressure": 0.3,
        "dot_pct": 0.0,
        "wickets": 1,
        "runs": 8,
        "actual_rr": 8.0,
        "flag": "above_average"
      },
      {
        "over": 19,
        "pressure": 0.48,
        "dot_pct": 0.0,
        "wickets": 0,
        "runs": 4,
        "actual_rr": 24.0,
        "flag": "high"
      }
    ],
    "baselines": {
      "innings1": {
        "overall": 0.261,
        "powerplay_avg": 0.376,
        "death_avg": 0.185,
        "p75": 0.354,
        "p90": 0.457
      },
      "innings2": {
        "overall": 0.293,
        "powerplay_avg": 0.341,
        "death_avg": 0.275,
        "p75": 0.396,
        "p90": 0.482
      }
    },
    "heatmap_grid": {
      "innings1": {
        "matrix": [
          [
            null,
            null,
            null,
            null,
            null,
            null,
            null,
            null,
            null,
            null,
            null,
            null,
            null,
            null,
            null,
            null,
            null,
            null,
            null,
            null,
            null
          ],
          [
            null,
            null,
            null,
            null,
            null,
            null,
            null,
            null,
            null,
            null,
            null,
            null,
            null,
            null,
            null,
            null,
            null,
            null,
            null,
            null,
            null
          ],
          [
            null,
            null,
            null,
            null,
            null,
            null,
            null,
            null,
            null,
            null,
            null,
            null,
            null,
            null,
            null,
            null,
            null,
            null,
            null,
            null,
            null
          ],
          [
            null,
            null,
            null,
            null,
            null,
            null,
            null,
            null,
            null,
            null,
            null,
            null,
            null,
            null,
            null,
            null,
            null,
            null,
            null,
            null,
            null
          ],
          [
            null,
            null,
            null,
            null,
            null,
            null,
            null,
            null,
            null,
            null,
            null,
            null,
            null,
            null,
            null,
            null,
            null,
            null,
            null,
            null,
            null
          ],
          [
            null,
            null,
            null,
            null,
            null,
            null,
            null,
            null,
            null,
            null,
            null,
            null,
            null,
            null,
            null,
            null,
            null,
            null,
            null,
            null,
            null
          ],
          [
            null,
            0.097,
            null,
            null,
            null,
            null,
            null,
            null,
            null,
            null,
            null,
            null,
            null,
            null,
            null,
            null,
            null,
            null,
            null,
            null,
            null
          ],
          [
            null,
            null,
            0.33,
            0.067,
            0.247,
            0.097,
            0.337,
            null,
            null,
            null,
            null,
            null,
            null,
            null,
            null,
            null,
            null,
            null,
            null,
            null,
            null
          ],
          [
            null,
            null,
            null,
            null,
            null,
            null,
            null,
            0.493,
            0.133,
            0.157,
            0.26,
            0.06,
            null,
            null,
            null,
            null,
            null,
            null,
            null,
            null,
            null
          ],
          [
            null,
            null,
            null,
            null,
            null,
            null,
            null,
            null,
            null,
            null,
            null,
            null,
            0.33,
            0.06,
            0.307,
            null,
            null,
            null,
            null,
            null,
            null
          ],
          [
            null,
            null,
            null,
            null,
            null,
            null,
            null,
            null,
            null,
            null,
            null,
            null,
            null,
            null,
            null,
            0.427,
            0.157,
            0.547,
            0.403,
            0.453,
            0.267
          ]
        ],
        "x_labels": [
          20,
          19,
          18,
          17,
          16,
          15,
          14,
          13,
          12,
          11,
          10,
          9,
          8,
          7,
          6,
          5,
          4,
          3,
          2,
          1,
          0
        ],
        "y_labels": [
          10,
          9,
          8,
          7,
          6,
          5,
          4,
          3,
          2,
          1,
          0
        ]
      },
      "innings2": {
        "matrix": [
          [
            null,
            null,
            null,
            null,
            null,
            null,
            null,
            null,
            null,
            null,
            null,
            null,
            null,
            null,
            null,
            null,
            null,
            null,
            null,
            null,
            null
          ],
          [
            null,
            null,
            null,
            null,
            null,
            null,
            null,
            null,
            null,
            null,
            null,
            null,
            null,
            null,
            null,
            null,
            null,
            null,
            null,
            null,
            null
          ],
          [
            null,
            null,
            null,
            null,
            null,
            null,
            null,
            null,
            null,
            null,
            null,
            null,
            null,
            null,
            null,
            null,
            null,
            null,
            null,
            null,
            null
          ],
          [
            null,
            null,
            null,
            null,
            null,
            null,
            null,
            null,
            null,
            null,
            null,
            null,
            null,
            null,
            null,
            null,
            null,
            null,
            null,
            null,
            null
          ],
          [
            null,
            null,
            null,
            null,
            null,
            null,
            null,
            null,
            null,
            null,
            null,
            null,
            null,
            null,
            null,
            null,
            null,
            null,
            null,
            null,
            null
          ],
          [
            null,
            null,
            null,
            null,
            null,
            null,
            null,
            null,
            null,
            null,
            null,
            null,
            null,
            null,
            null,
            null,
            null,
            null,
            null,
            null,
            null
          ],
          [
            null,
            0.48,
            null,
            null,
            null,
            null,
            null,
            null,
            null,
            null,
            null,
            null,
            null,
            null,
            null,
            null,
            null,
            null,
            null,
            null,
            null
          ],
          [
            null,
            null,
            0.3,
            0.157,
            0.163,
            null,
            null,
            null,
            null,
            null,
            null,
            null,
            null,
            null,
            null,
            null,
            null,
            null,
            null,
            null,
            null
          ],
          [
            null,
            null,
            null,
            null,
            null,
            0.463,
            null,
            null,
            null,
            null,
            null,
            null,
            null,
            null,
            null,
            null,
            null,
            null,
            null,
            null,
            null
          ],
          [
            null,
            null,
            null,
            null,
            null,
            null,
            0.5,
            0.157,
            0.127,
            null,
            null,
            null,
            null,
            null,
            null,
            null,
            null,
            null,
            null,
            null,
            null
          ],
          [
            null,
            null,
            null,
            null,
            null,
            null,
            null,
            null,
            null,
            0.54,
            0.217,
            0.127,
            0.313,
            0.067,
            0.2,
            0.373,
            0.343,
            0.277,
            0.463,
            0.23,
            0.357
          ]
        ],
        "x_labels": [
          20,
          19,
          18,
          17,
          16,
          15,
          14,
          13,
          12,
          11,
          10,
          9,
          8,
          7,
          6,
          5,
          4,
          3,
          2,
          1,
          0
        ],
        "y_labels": [
          10,
          9,
          8,
          7,
          6,
          5,
          4,
          3,
          2,
          1,
          0
        ]
      }
    }
  },
  "win_probability": [
    {
      "ball_index": 1,
      "over_ball": "0.1",
      "current_score": 1,
      "wickets_fallen": 0,
      "balls_remaining": 119,
      "win_prob": 0.5167,
      "boundary_type": null,
      "is_wicket": false,
      "par_score": 0.0,
      "runs_off_bat": 1
    },
    {
      "ball_index": 2,
      "over_ball": "0.2",
      "current_score": 1,
      "wickets_fallen": 0,
      "balls_remaining": 118,
      "win_prob": 0.5167,
      "boundary_type": null,
      "is_wicket": false,
      "par_score": 0.0,
      "runs_off_bat": 0
    },
    {
      "ball_index": 3,
      "over_ball": "0.3",
      "current_score": 5,
      "wickets_fallen": 0,
      "balls_remaining": 117,
      "win_prob": 0.5826,
      "boundary_type": "four",
      "is_wicket": false,
      "par_score": 0.0,
      "runs_off_bat": 4
    },
    {
      "ball_index": 4,
      "over_ball": "0.4",
      "current_score": 5,
      "wickets_fallen": 0,
      "balls_remaining": 116,
      "win_prob": 0.5826,
      "boundary_type": null,
      "is_wicket": false,
      "par_score": 0.0,
      "runs_off_bat": 0
    },
    {
      "ball_index": 5,
      "over_ball": "0.5",
      "current_score": 5,
      "wickets_fallen": 0,
      "balls_remaining": 115,
      "win_prob": 0.5826,
      "boundary_type": null,
      "is_wicket": false,
      "par_score": 0.0,
      "runs_off_bat": 0
    },
    {
      "ball_index": 6,
      "over_ball": "0.6",
      "current_score": 5,
      "wickets_fallen": 0,
      "balls_remaining": 114,
      "win_prob": 0.5826,
      "boundary_type": null,
      "is_wicket": false,
      "par_score": 0.0,
      "runs_off_bat": 0
    },
    {
      "ball_index": 7,
      "over_ball": "1.1",
      "current_score": 5,
      "wickets_fallen": 0,
      "balls_remaining": 113,
      "win_prob": 0.5826,
      "boundary_type": null,
      "is_wicket": false,
      "par_score": 0.0,
      "runs_off_bat": 0
    },
    {
      "ball_index": 8,
      "over_ball": "1.2",
      "current_score": 5,
      "wickets_fallen": 0,
      "balls_remaining": 112,
      "win_prob": 0.5826,
      "boundary_type": null,
      "is_wicket": false,
      "par_score": 0.0,
      "runs_off_bat": 0
    },
    {
      "ball_index": 9,
      "over_ball": "1.3",
      "current_score": 9,
      "wickets_fallen": 0,
      "balls_remaining": 111,
      "win_prob": 0.6457,
      "boundary_type": "four",
      "is_wicket": false,
      "par_score": 0.0,
      "runs_off_bat": 4
    },
    {
      "ball_index": 10,
      "over_ball": "1.4",
      "current_score": 10,
      "wickets_fallen": 0,
      "balls_remaining": 110,
      "win_prob": 0.6608,
      "boundary_type": null,
      "is_wicket": false,
      "par_score": 0.0,
      "runs_off_bat": 1
    },
    {
      "ball_index": 11,
      "over_ball": "1.5",
      "current_score": 14,
      "wickets_fallen": 0,
      "balls_remaining": 109,
      "win_prob": 0.7178,
      "boundary_type": "four",
      "is_wicket": false,
      "par_score": 0.0,
      "runs_off_bat": 4
    },
    {
      "ball_index": 12,
      "over_ball": "1.6",
      "current_score": 14,
      "wickets_fallen": 0,
      "balls_remaining": 108,
      "win_prob": 0.7178,
      "boundary_type": null,
      "is_wicket": false,
      "par_score": 0.0,
      "runs_off_bat": 0
    },
    {
      "ball_index": 13,
      "over_ball": "2.1",
      "current_score": 14,
      "wickets_fallen": 0,
      "balls_remaining": 107,
      "win_prob": 0.7178,
      "boundary_type": null,
      "is_wicket": false,
      "par_score": 0.0,
      "runs_off_bat": 0
    },
    {
      "ball_index": 14,
      "over_ball": "2.2",
      "current_score": 20,
      "wickets_fallen": 0,
      "balls_remaining": 106,
      "win_prob": 0.7914,
      "boundary_type": "six",
      "is_wicket": false,
      "par_score": 0.0,
      "runs_off_bat": 6
    },
    {
      "ball_index": 15,
      "over_ball": "2.3",
      "current_score": 21,
      "wickets_fallen": 0,
      "balls_remaining": 105,
      "win_prob": 0.8022,
      "boundary_type": null,
      "is_wicket": false,
      "par_score": 0.0,
      "runs_off_bat": 1
    },
    {
      "ball_index": 16,
      "over_ball": "2.4",
      "current_score": 21,
      "wickets_fallen": 0,
      "balls_remaining": 104,
      "win_prob": 0.8022,
      "boundary_type": null,
      "is_wicket": false,
      "par_score": 0.0,
      "runs_off_bat": 0
    },
    {
      "ball_index": 17,
      "over_ball": "2.5",
      "current_score": 27,
      "wickets_fallen": 0,
      "balls_remaining": 103,
      "win_prob": 0.8581,
      "boundary_type": "six",
      "is_wicket": false,
      "par_score": 0.0,
      "runs_off_bat": 6
    },
    {
      "ball_index": 18,
      "over_ball": "2.6",
      "current_score": 33,
      "wickets_fallen": 0,
      "balls_remaining": 102,
      "win_prob": 0.9002,
      "boundary_type": "six",
      "is_wicket": false,
      "par_score": 0.0,
      "runs_off_bat": 6
    },
    {
      "ball_index": 19,
      "over_ball": "3.1",
      "current_score": 39,
      "wickets_fallen": 0,
      "balls_remaining": 101,
      "win_prob": 0.9309,
      "boundary_type": "six",
      "is_wicket": false,
      "par_score": 0.0,
      "runs_off_bat": 6
    },
    {
      "ball_index": 20,
      "over_ball": "3.2",
      "current_score": 40,
      "wickets_fallen": 0,
      "balls_remaining": 100,
      "win_prob": 0.935,
      "boundary_type": null,
      "is_wicket": false,
      "par_score": 0.0,
      "runs_off_bat": 1
    },
    {
      "ball_index": 21,
      "over_ball": "3.3",
      "current_score": 41,
      "wickets_fallen": 0,
      "balls_remaining": 99,
      "win_prob": 0.939,
      "boundary_type": null,
      "is_wicket": false,
      "par_score": 0.0,
      "runs_off_bat": 1
    },
    {
      "ball_index": 22,
      "over_ball": "3.4",
      "current_score": 42,
      "wickets_fallen": 0,
      "balls_remaining": 98,
      "win_prob": 0.9427,
      "boundary_type": null,
      "is_wicket": false,
      "par_score": 0.0,
      "runs_off_bat": 1
    },
    {
      "ball_index": 23,
      "over_ball": "3.5",
      "current_score": 48,
      "wickets_fallen": 0,
      "balls_remaining": 97,
      "win_prob": 0.9608,
      "boundary_type": "six",
      "is_wicket": false,
      "par_score": 0.0,
      "runs_off_bat": 6
    },
    {
      "ball_index": 24,
      "over_ball": "3.6",
      "current_score": 48,
      "wickets_fallen": 0,
      "balls_remaining": 96,
      "win_prob": 0.9608,
      "boundary_type": null,
      "is_wicket": false,
      "par_score": 0.0,
      "runs_off_bat": 0
    },
    {
      "ball_index": 25,
      "over_ball": "4.1",
      "current_score": 52,
      "wickets_fallen": 0,
      "balls_remaining": 95,
      "win_prob": 0.9697,
      "boundary_type": "four",
      "is_wicket": false,
      "par_score": 0.0,
      "runs_off_bat": 4
    },
    {
      "ball_index": 26,
      "over_ball": "4.2",
      "current_score": 58,
      "wickets_fallen": 0,
      "balls_remaining": 94,
      "win_prob": 0.9795,
      "boundary_type": "six",
      "is_wicket": false,
      "par_score": 0.0,
      "runs_off_bat": 6
    },
    {
      "ball_index": 27,
      "over_ball": "4.3",
      "current_score": 58,
      "wickets_fallen": 0,
      "balls_remaining": 93,
      "win_prob": 0.9795,
      "boundary_type": null,
      "is_wicket": false,
      "par_score": 0.0,
      "runs_off_bat": 0
    },
    {
      "ball_index": 28,
      "over_ball": "4.4",
      "current_score": 62,
      "wickets_fallen": 0,
      "balls_remaining": 92,
      "win_prob": 0.98,
      "boundary_type": "four",
      "is_wicket": false,
      "par_score": 0.0,
      "runs_off_bat": 4
    },
    {
      "ball_index": 29,
      "over_ball": "4.5",
      "current_score": 62,
      "wickets_fallen": 0,
      "balls_remaining": 91,
      "win_prob": 0.98,
      "boundary_type": null,
      "is_wicket": false,
      "par_score": 0.0,
      "runs_off_bat": 0
    },
    {
      "ball_index": 30,
      "over_ball": "4.6",
      "current_score": 63,
      "wickets_fallen": 0,
      "balls_remaining": 90,
      "win_prob": 0.98,
      "boundary_type": null,
      "is_wicket": false,
      "par_score": 0.0,
      "runs_off_bat": 1
    },
    {
      "ball_index": 31,
      "over_ball": "5.1",
      "current_score": 69,
      "wickets_fallen": 0,
      "balls_remaining": 89,
      "win_prob": 0.98,
      "boundary_type": "six",
      "is_wicket": false,
      "par_score": 0.0,
      "runs_off_bat": 6
    },
    {
      "ball_index": 32,
      "over_ball": "5.2",
      "current_score": 71,
      "wickets_fallen": 0,
      "balls_remaining": 88,
      "win_prob": 0.98,
      "boundary_type": null,
      "is_wicket": false,
      "par_score": 0.0,
      "runs_off_bat": 2
    },
    {
      "ball_index": 33,
      "over_ball": "5.3",
      "current_score": 71,
      "wickets_fallen": 0,
      "balls_remaining": 87,
      "win_prob": 0.98,
      "boundary_type": null,
      "is_wicket": false,
      "par_score": 0.0,
      "runs_off_bat": 0
    },
    {
      "ball_index": 34,
      "over_ball": "5.4",
      "current_score": 77,
      "wickets_fallen": 0,
      "balls_remaining": 86,
      "win_prob": 0.98,
      "boundary_type": "six",
      "is_wicket": false,
      "par_score": 0.0,
      "runs_off_bat": 6
    },
    {
      "ball_index": 35,
      "over_ball": "5.5",
      "current_score": 77,
      "wickets_fallen": 0,
      "balls_remaining": 85,
      "win_prob": 0.98,
      "boundary_type": null,
      "is_wicket": false,
      "par_score": 0.0,
      "runs_off_bat": 0
    },
    {
      "ball_index": 36,
      "over_ball": "5.6",
      "current_score": 79,
      "wickets_fallen": 0,
      "balls_remaining": 84,
      "win_prob": 0.98,
      "boundary_type": null,
      "is_wicket": false,
      "par_score": 0.0,
      "runs_off_bat": 2
    },
    {
      "ball_index": 37,
      "over_ball": "6.1",
      "current_score": 80,
      "wickets_fallen": 0,
      "balls_remaining": 83,
      "win_prob": 0.98,
      "boundary_type": null,
      "is_wicket": false,
      "par_score": 0.0,
      "runs_off_bat": 1
    },
    {
      "ball_index": 38,
      "over_ball": "6.2",
      "current_score": 80,
      "wickets_fallen": 0,
      "balls_remaining": 82,
      "win_prob": 0.98,
      "boundary_type": null,
      "is_wicket": false,
      "par_score": 0.0,
      "runs_off_bat": 0
    },
    {
      "ball_index": 39,
      "over_ball": "6.3",
      "current_score": 81,
      "wickets_fallen": 0,
      "balls_remaining": 81,
      "win_prob": 0.98,
      "boundary_type": null,
      "is_wicket": false,
      "par_score": 0.0,
      "runs_off_bat": 1
    },
    {
      "ball_index": 40,
      "over_ball": "6.4",
      "current_score": 87,
      "wickets_fallen": 0,
      "balls_remaining": 80,
      "win_prob": 0.98,
      "boundary_type": "six",
      "is_wicket": false,
      "par_score": 0.0,
      "runs_off_bat": 6
    },
    {
      "ball_index": 41,
      "over_ball": "6.5",
      "current_score": 87,
      "wickets_fallen": 0,
      "balls_remaining": 79,
      "win_prob": 0.98,
      "boundary_type": null,
      "is_wicket": false,
      "par_score": 0.0,
      "runs_off_bat": 0
    },
    {
      "ball_index": 42,
      "over_ball": "6.6",
      "current_score": 87,
      "wickets_fallen": 0,
      "balls_remaining": 78,
      "win_prob": 0.98,
      "boundary_type": null,
      "is_wicket": false,
      "par_score": 0.0,
      "runs_off_bat": 0
    },
    {
      "ball_index": 43,
      "over_ball": "7.1",
      "current_score": 88,
      "wickets_fallen": 0,
      "balls_remaining": 77,
      "win_prob": 0.98,
      "boundary_type": null,
      "is_wicket": false,
      "par_score": 0.0,
      "runs_off_bat": 1
    },
    {
      "ball_index": 44,
      "over_ball": "7.2",
      "current_score": 89,
      "wickets_fallen": 0,
      "balls_remaining": 76,
      "win_prob": 0.98,
      "boundary_type": null,
      "is_wicket": false,
      "par_score": 0.0,
      "runs_off_bat": 1
    },
    {
      "ball_index": 45,
      "over_ball": "7.3",
      "current_score": 93,
      "wickets_fallen": 0,
      "balls_remaining": 75,
      "win_prob": 0.98,
      "boundary_type": "four",
      "is_wicket": false,
      "par_score": 0.0,
      "runs_off_bat": 4
    },
    {
      "ball_index": 46,
      "over_ball": "7.4",
      "current_score": 94,
      "wickets_fallen": 0,
      "balls_remaining": 74,
      "win_prob": 0.98,
      "boundary_type": null,
      "is_wicket": false,
      "par_score": 0.0,
      "runs_off_bat": 1
    },
    {
      "ball_index": 47,
      "over_ball": "7.5",
      "current_score": 94,
      "wickets_fallen": 0,
      "balls_remaining": 73,
      "win_prob": 0.98,
      "boundary_type": null,
      "is_wicket": false,
      "par_score": 0.0,
      "runs_off_bat": 0
    },
    {
      "ball_index": 48,
      "over_ball": "7.6",
      "current_score": 95,
      "wickets_fallen": 0,
      "balls_remaining": 72,
      "win_prob": 0.98,
      "boundary_type": null,
      "is_wicket": false,
      "par_score": 0.0,
      "runs_off_bat": 1
    },
    {
      "ball_index": 49,
      "over_ball": "8.1",
      "current_score": 101,
      "wickets_fallen": 0,
      "balls_remaining": 71,
      "win_prob": 0.98,
      "boundary_type": "six",
      "is_wicket": false,
      "par_score": 0.0,
      "runs_off_bat": 6
    },
    {
      "ball_index": 50,
      "over_ball": "8.2",
      "current_score": 101,
      "wickets_fallen": 0,
      "balls_remaining": 70,
      "win_prob": 0.98,
      "boundary_type": null,
      "is_wicket": false,
      "par_score": 0.0,
      "runs_off_bat": 0
    },
    {
      "ball_index": 51,
      "over_ball": "8.3",
      "current_score": 107,
      "wickets_fallen": 0,
      "balls_remaining": 69,
      "win_prob": 0.98,
      "boundary_type": "six",
      "is_wicket": false,
      "par_score": 0.0,
      "runs_off_bat": 6
    },
    {
      "ball_index": 52,
      "over_ball": "8.4",
      "current_score": 108,
      "wickets_fallen": 0,
      "balls_remaining": 68,
      "win_prob": 0.98,
      "boundary_type": null,
      "is_wicket": false,
      "par_score": 0.0,
      "runs_off_bat": 1
    },
    {
      "ball_index": 53,
      "over_ball": "8.5",
      "current_score": 109,
      "wickets_fallen": 0,
      "balls_remaining": 67,
      "win_prob": 0.98,
      "boundary_type": null,
      "is_wicket": false,
      "par_score": 0.0,
      "runs_off_bat": 1
    },
    {
      "ball_index": 54,
      "over_ball": "8.6",
      "current_score": 109,
      "wickets_fallen": 0,
      "balls_remaining": 66,
      "win_prob": 0.98,
      "boundary_type": null,
      "is_wicket": false,
      "par_score": 0.0,
      "runs_off_bat": 0
    },
    {
      "ball_index": 55,
      "over_ball": "9.1",
      "current_score": 109,
      "wickets_fallen": 0,
      "balls_remaining": 65,
      "win_prob": 0.98,
      "boundary_type": null,
      "is_wicket": false,
      "par_score": 0.0,
      "runs_off_bat": 0
    },
    {
      "ball_index": 56,
      "over_ball": "9.2",
      "current_score": 111,
      "wickets_fallen": 0,
      "balls_remaining": 64,
      "win_prob": 0.98,
      "boundary_type": null,
      "is_wicket": false,
      "par_score": 0.0,
      "runs_off_bat": 2
    },
    {
      "ball_index": 57,
      "over_ball": "9.3",
      "current_score": 112,
      "wickets_fallen": 0,
      "balls_remaining": 63,
      "win_prob": 0.98,
      "boundary_type": null,
      "is_wicket": false,
      "par_score": 0.0,
      "runs_off_bat": 1
    },
    {
      "ball_index": 58,
      "over_ball": "9.4",
      "current_score": 116,
      "wickets_fallen": 0,
      "balls_remaining": 62,
      "win_prob": 0.98,
      "boundary_type": "four",
      "is_wicket": false,
      "par_score": 0.0,
      "runs_off_bat": 4
    },
    {
      "ball_index": 59,
      "over_ball": "9.5",
      "current_score": 117,
      "wickets_fallen": 0,
      "balls_remaining": 61,
      "win_prob": 0.98,
      "boundary_type": null,
      "is_wicket": false,
      "par_score": 0.0,
      "runs_off_bat": 1
    },
    {
      "ball_index": 60,
      "over_ball": "9.6",
      "current_score": 119,
      "wickets_fallen": 0,
      "balls_remaining": 60,
      "win_prob": 0.98,
      "boundary_type": null,
      "is_wicket": false,
      "par_score": 0.0,
      "runs_off_bat": 2
    },
    {
      "ball_index": 61,
      "over_ball": "10.1",
      "current_score": 120,
      "wickets_fallen": 0,
      "balls_remaining": 59,
      "win_prob": 0.98,
      "boundary_type": null,
      "is_wicket": false,
      "par_score": 3.7,
      "runs_off_bat": 1
    },
    {
      "ball_index": 62,
      "over_ball": "10.2",
      "current_score": 126,
      "wickets_fallen": 0,
      "balls_remaining": 58,
      "win_prob": 0.98,
      "boundary_type": "six",
      "is_wicket": false,
      "par_score": 7.4,
      "runs_off_bat": 6
    },
    {
      "ball_index": 63,
      "over_ball": "10.3",
      "current_score": 126,
      "wickets_fallen": 0,
      "balls_remaining": 57,
      "win_prob": 0.98,
      "boundary_type": null,
      "is_wicket": false,
      "par_score": 11.1,
      "runs_off_bat": 0
    },
    {
      "ball_index": 64,
      "over_ball": "10.4",
      "current_score": 127,
      "wickets_fallen": 0,
      "balls_remaining": 56,
      "win_prob": 0.98,
      "boundary_type": null,
      "is_wicket": false,
      "par_score": 14.7,
      "runs_off_bat": 1
    },
    {
      "ball_index": 65,
      "over_ball": "10.5",
      "current_score": 128,
      "wickets_fallen": 0,
      "balls_remaining": 55,
      "win_prob": 0.98,
      "boundary_type": null,
      "is_wicket": false,
      "par_score": 18.4,
      "runs_off_bat": 1
    },
    {
      "ball_index": 66,
      "over_ball": "10.6",
      "current_score": 132,
      "wickets_fallen": 0,
      "balls_remaining": 54,
      "win_prob": 0.98,
      "boundary_type": "four",
      "is_wicket": false,
      "par_score": 22.1,
      "runs_off_bat": 4
    },
    {
      "ball_index": 67,
      "over_ball": "11.1",
      "current_score": 136,
      "wickets_fallen": 0,
      "balls_remaining": 53,
      "win_prob": 0.98,
      "boundary_type": "four",
      "is_wicket": false,
      "par_score": 25.8,
      "runs_off_bat": 4
    },
    {
      "ball_index": 68,
      "over_ball": "11.2",
      "current_score": 142,
      "wickets_fallen": 0,
      "balls_remaining": 52,
      "win_prob": 0.98,
      "boundary_type": "six",
      "is_wicket": false,
      "par_score": 29.5,
      "runs_off_bat": 6
    },
    {
      "ball_index": 69,
      "over_ball": "11.3",
      "current_score": 143,
      "wickets_fallen": 0,
      "balls_remaining": 51,
      "win_prob": 0.98,
      "boundary_type": null,
      "is_wicket": false,
      "par_score": 33.2,
      "runs_off_bat": 1
    },
    {
      "ball_index": 70,
      "over_ball": "11.4",
      "current_score": 144,
      "wickets_fallen": 0,
      "balls_remaining": 50,
      "win_prob": 0.98,
      "boundary_type": null,
      "is_wicket": false,
      "par_score": 36.8,
      "runs_off_bat": 1
    },
    {
      "ball_index": 71,
      "over_ball": "11.5",
      "current_score": 144,
      "wickets_fallen": 1,
      "balls_remaining": 49,
      "win_prob": 0.98,
      "boundary_type": null,
      "is_wicket": true,
      "par_score": 58.6,
      "runs_off_bat": 0
    },
    {
      "ball_index": 72,
      "over_ball": "11.6",
      "current_score": 148,
      "wickets_fallen": 1,
      "balls_remaining": 48,
      "win_prob": 0.98,
      "boundary_type": "four",
      "is_wicket": false,
      "par_score": 61.9,
      "runs_off_bat": 4
    },
    {
      "ball_index": 73,
      "over_ball": "12.1",
      "current_score": 148,
      "wickets_fallen": 1,
      "balls_remaining": 47,
      "win_prob": 0.98,
      "boundary_type": null,
      "is_wicket": false,
      "par_score": 65.2,
      "runs_off_bat": 0
    },
    {
      "ball_index": 74,
      "over_ball": "12.2",
      "current_score": 149,
      "wickets_fallen": 1,
      "balls_remaining": 46,
      "win_prob": 0.98,
      "boundary_type": null,
      "is_wicket": false,
      "par_score": 68.5,
      "runs_off_bat": 1
    },
    {
      "ball_index": 75,
      "over_ball": "12.3",
      "current_score": 150,
      "wickets_fallen": 1,
      "balls_remaining": 45,
      "win_prob": 0.98,
      "boundary_type": null,
      "is_wicket": false,
      "par_score": 71.8,
      "runs_off_bat": 1
    },
    {
      "ball_index": 76,
      "over_ball": "12.4",
      "current_score": 151,
      "wickets_fallen": 1,
      "balls_remaining": 44,
      "win_prob": 0.98,
      "boundary_type": null,
      "is_wicket": false,
      "par_score": 75.1,
      "runs_off_bat": 1
    },
    {
      "ball_index": 77,
      "over_ball": "12.5",
      "current_score": 152,
      "wickets_fallen": 1,
      "balls_remaining": 43,
      "win_prob": 0.98,
      "boundary_type": null,
      "is_wicket": false,
      "par_score": 78.5,
      "runs_off_bat": 1
    },
    {
      "ball_index": 78,
      "over_ball": "12.6",
      "current_score": 158,
      "wickets_fallen": 1,
      "balls_remaining": 42,
      "win_prob": 0.98,
      "boundary_type": "six",
      "is_wicket": false,
      "par_score": 81.8,
      "runs_off_bat": 6
    },
    {
      "ball_index": 79,
      "over_ball": "13.1",
      "current_score": 162,
      "wickets_fallen": 1,
      "balls_remaining": 41,
      "win_prob": 0.98,
      "boundary_type": "four",
      "is_wicket": false,
      "par_score": 85.1,
      "runs_off_bat": 4
    },
    {
      "ball_index": 80,
      "over_ball": "13.2",
      "current_score": 163,
      "wickets_fallen": 1,
      "balls_remaining": 40,
      "win_prob": 0.98,
      "boundary_type": null,
      "is_wicket": false,
      "par_score": 88.4,
      "runs_off_bat": 1
    },
    {
      "ball_index": 81,
      "over_ball": "13.3",
      "current_score": 164,
      "wickets_fallen": 1,
      "balls_remaining": 39,
      "win_prob": 0.98,
      "boundary_type": null,
      "is_wicket": false,
      "par_score": 91.7,
      "runs_off_bat": 1
    },
    {
      "ball_index": 82,
      "over_ball": "13.4",
      "current_score": 165,
      "wickets_fallen": 1,
      "balls_remaining": 38,
      "win_prob": 0.98,
      "boundary_type": null,
      "is_wicket": false,
      "par_score": 95.0,
      "runs_off_bat": 1
    },
    {
      "ball_index": 83,
      "over_ball": "13.5",
      "current_score": 165,
      "wickets_fallen": 1,
      "balls_remaining": 37,
      "win_prob": 0.98,
      "boundary_type": null,
      "is_wicket": false,
      "par_score": 98.3,
      "runs_off_bat": 0
    },
    {
      "ball_index": 84,
      "over_ball": "13.6",
      "current_score": 169,
      "wickets_fallen": 1,
      "balls_remaining": 36,
      "win_prob": 0.98,
      "boundary_type": "four",
      "is_wicket": false,
      "par_score": 101.7,
      "runs_off_bat": 4
    },
    {
      "ball_index": 85,
      "over_ball": "14.1",
      "current_score": 173,
      "wickets_fallen": 1,
      "balls_remaining": 35,
      "win_prob": 0.98,
      "boundary_type": "four",
      "is_wicket": false,
      "par_score": 105.0,
      "runs_off_bat": 4
    },
    {
      "ball_index": 86,
      "over_ball": "14.2",
      "current_score": 173,
      "wickets_fallen": 2,
      "balls_remaining": 34,
      "win_prob": 0.9701,
      "boundary_type": null,
      "is_wicket": true,
      "par_score": 120.8,
      "runs_off_bat": 0
    },
    {
      "ball_index": 87,
      "over_ball": "14.3",
      "current_score": 177,
      "wickets_fallen": 2,
      "balls_remaining": 33,
      "win_prob": 0.9721,
      "boundary_type": "four",
      "is_wicket": false,
      "par_score": 123.8,
      "runs_off_bat": 4
    },
    {
      "ball_index": 88,
      "over_ball": "14.4",
      "current_score": 177,
      "wickets_fallen": 2,
      "balls_remaining": 32,
      "win_prob": 0.9662,
      "boundary_type": null,
      "is_wicket": false,
      "par_score": 126.7,
      "runs_off_bat": 0
    },
    {
      "ball_index": 89,
      "over_ball": "14.5",
      "current_score": 177,
      "wickets_fallen": 2,
      "balls_remaining": 31,
      "win_prob": 0.9592,
      "boundary_type": null,
      "is_wicket": false,
      "par_score": 129.7,
      "runs_off_bat": 0
    },
    {
      "ball_index": 90,
      "over_ball": "14.6",
      "current_score": 177,
      "wickets_fallen": 2,
      "balls_remaining": 30,
      "win_prob": 0.9507,
      "boundary_type": null,
      "is_wicket": false,
      "par_score": 132.6,
      "runs_off_bat": 0
    },
    {
      "ball_index": 91,
      "over_ball": "15.1",
      "current_score": 177,
      "wickets_fallen": 2,
      "balls_remaining": 29,
      "win_prob": 0.9407,
      "boundary_type": null,
      "is_wicket": false,
      "par_score": 135.5,
      "runs_off_bat": 0
    },
    {
      "ball_index": 92,
      "over_ball": "15.2",
      "current_score": 177,
      "wickets_fallen": 3,
      "balls_remaining": 28,
      "win_prob": 0.8676,
      "boundary_type": null,
      "is_wicket": true,
      "par_score": 148.8,
      "runs_off_bat": 0
    },
    {
      "ball_index": 93,
      "over_ball": "15.3",
      "current_score": 178,
      "wickets_fallen": 3,
      "balls_remaining": 27,
      "win_prob": 0.855,
      "boundary_type": null,
      "is_wicket": false,
      "par_score": 151.4,
      "runs_off_bat": 1
    },
    {
      "ball_index": 94,
      "over_ball": "15.4",
      "current_score": 182,
      "wickets_fallen": 3,
      "balls_remaining": 26,
      "win_prob": 0.8664,
      "boundary_type": "four",
      "is_wicket": false,
      "par_score": 154.0,
      "runs_off_bat": 4
    },
    {
      "ball_index": 95,
      "over_ball": "15.5",
      "current_score": 186,
      "wickets_fallen": 3,
      "balls_remaining": 25,
      "win_prob": 0.877,
      "boundary_type": "four",
      "is_wicket": false,
      "par_score": 156.5,
      "runs_off_bat": 4
    },
    {
      "ball_index": 96,
      "over_ball": "15.6",
      "current_score": 186,
      "wickets_fallen": 3,
      "balls_remaining": 24,
      "win_prob": 0.8572,
      "boundary_type": null,
      "is_wicket": false,
      "par_score": 159.1,
      "runs_off_bat": 0
    },
    {
      "ball_index": 97,
      "over_ball": "16.1",
      "current_score": 187,
      "wickets_fallen": 3,
      "balls_remaining": 23,
      "win_prob": 0.8438,
      "boundary_type": null,
      "is_wicket": false,
      "par_score": 161.7,
      "runs_off_bat": 1
    },
    {
      "ball_index": 98,
      "over_ball": "16.2",
      "current_score": 188,
      "wickets_fallen": 3,
      "balls_remaining": 22,
      "win_prob": 0.8294,
      "boundary_type": null,
      "is_wicket": false,
      "par_score": 164.3,
      "runs_off_bat": 1
    },
    {
      "ball_index": 99,
      "over_ball": "16.3",
      "current_score": 188,
      "wickets_fallen": 3,
      "balls_remaining": 21,
      "win_prob": 0.8037,
      "boundary_type": null,
      "is_wicket": false,
      "par_score": 166.9,
      "runs_off_bat": 0
    },
    {
      "ball_index": 100,
      "over_ball": "16.4",
      "current_score": 188,
      "wickets_fallen": 3,
      "balls_remaining": 20,
      "win_prob": 0.7752,
      "boundary_type": null,
      "is_wicket": false,
      "par_score": 169.4,
      "runs_off_bat": 0
    },
    {
      "ball_index": 101,
      "over_ball": "16.5",
      "current_score": 189,
      "wickets_fallen": 3,
      "balls_remaining": 19,
      "win_prob": 0.7563,
      "boundary_type": null,
      "is_wicket": false,
      "par_score": 172.0,
      "runs_off_bat": 1
    },
    {
      "ball_index": 102,
      "over_ball": "16.6",
      "current_score": 193,
      "wickets_fallen": 3,
      "balls_remaining": 18,
      "win_prob": 0.7734,
      "boundary_type": "four",
      "is_wicket": false,
      "par_score": 174.6,
      "runs_off_bat": 4
    },
    {
      "ball_index": 103,
      "over_ball": "17.1",
      "current_score": 193,
      "wickets_fallen": 3,
      "balls_remaining": 17,
      "win_prob": 0.7418,
      "boundary_type": null,
      "is_wicket": false,
      "par_score": 177.2,
      "runs_off_bat": 0
    },
    {
      "ball_index": 104,
      "over_ball": "17.2",
      "current_score": 194,
      "wickets_fallen": 3,
      "balls_remaining": 16,
      "win_prob": 0.7212,
      "boundary_type": null,
      "is_wicket": false,
      "par_score": 179.7,
      "runs_off_bat": 1
    },
    {
      "ball_index": 105,
      "over_ball": "17.3",
      "current_score": 198,
      "wickets_fallen": 3,
      "balls_remaining": 15,
      "win_prob": 0.7398,
      "boundary_type": "four",
      "is_wicket": false,
      "par_score": 182.3,
      "runs_off_bat": 4
    },
    {
      "ball_index": 106,
      "over_ball": "17.4",
      "current_score": 199,
      "wickets_fallen": 3,
      "balls_remaining": 14,
      "win_prob": 0.7191,
      "boundary_type": null,
      "is_wicket": false,
      "par_score": 184.9,
      "runs_off_bat": 1
    },
    {
      "ball_index": 107,
      "over_ball": "17.5",
      "current_score": 200,
      "wickets_fallen": 3,
      "balls_remaining": 13,
      "win_prob": 0.6973,
      "boundary_type": null,
      "is_wicket": false,
      "par_score": 187.5,
      "runs_off_bat": 1
    },
    {
      "ball_index": 108,
      "over_ball": "17.6",
      "current_score": 204,
      "wickets_fallen": 3,
      "balls_remaining": 12,
      "win_prob": 0.7169,
      "boundary_type": "four",
      "is_wicket": false,
      "par_score": 190.1,
      "runs_off_bat": 4
    },
    {
      "ball_index": 109,
      "over_ball": "18.1",
      "current_score": 205,
      "wickets_fallen": 3,
      "balls_remaining": 11,
      "win_prob": 0.6951,
      "boundary_type": null,
      "is_wicket": false,
      "par_score": 192.6,
      "runs_off_bat": 1
    },
    {
      "ball_index": 110,
      "over_ball": "18.2",
      "current_score": 206,
      "wickets_fallen": 3,
      "balls_remaining": 10,
      "win_prob": 0.6724,
      "boundary_type": null,
      "is_wicket": false,
      "par_score": 195.2,
      "runs_off_bat": 1
    },
    {
      "ball_index": 111,
      "over_ball": "18.3",
      "current_score": 207,
      "wickets_fallen": 3,
      "balls_remaining": 9,
      "win_prob": 0.6488,
      "boundary_type": null,
      "is_wicket": false,
      "par_score": 197.8,
      "runs_off_bat": 1
    },
    {
      "ball_index": 112,
      "over_ball": "18.4",
      "current_score": 207,
      "wickets_fallen": 4,
      "balls_remaining": 8,
      "win_prob": 0.561,
      "boundary_type": null,
      "is_wicket": true,
      "par_score": 203.3,
      "runs_off_bat": 0
    },
    {
      "ball_index": 113,
      "over_ball": "18.5",
      "current_score": 208,
      "wickets_fallen": 4,
      "balls_remaining": 7,
      "win_prob": 0.5411,
      "boundary_type": null,
      "is_wicket": false,
      "par_score": 205.5,
      "runs_off_bat": 1
    },
    {
      "ball_index": 114,
      "over_ball": "18.6",
      "current_score": 212,
      "wickets_fallen": 4,
      "balls_remaining": 6,
      "win_prob": 0.5705,
      "boundary_type": "four",
      "is_wicket": false,
      "par_score": 207.7,
      "runs_off_bat": 4
    },
    {
      "ball_index": 115,
      "over_ball": "19.1",
      "current_score": 216,
      "wickets_fallen": 4,
      "balls_remaining": 5,
      "win_prob": 0.5995,
      "boundary_type": "four",
      "is_wicket": false,
      "par_score": 209.9,
      "runs_off_bat": 4
    }
  ],
  "inflexion_points": [
    {
      "ball_index": 17,
      "over_ball": "2.6",
      "wp_before": 0.7178,
      "wp_after": 0.9002,
      "delta": 0.1824,
      "abs_delta": 0.1824
    },
    {
      "ball_index": 112,
      "over_ball": "18.5",
      "wp_before": 0.7169,
      "wp_after": 0.5411,
      "delta": -0.1758,
      "abs_delta": 0.17579999999999996
    },
    {
      "ball_index": 92,
      "over_ball": "15.3",
      "wp_before": 0.9662,
      "wp_after": 0.855,
      "delta": -0.1112,
      "abs_delta": 0.11119999999999997
    }
  ],
  "volatility_index": {
    "value": 1.0,
    "interpretation": "One-sided \u2014 dominant throughout"
  },
  "burn_rate": {
    "innings1": [
      {
        "over": 0,
        "runs": 8,
        "wickets": 0,
        "run_rate": 8.0,
        "classification": "Efficient",
        "wickets_remaining_start": 10,
        "wickets_remaining_end": 10,
        "balls": 6
      },
      {
        "over": 1,
        "runs": 4,
        "wickets": 0,
        "run_rate": 4.0,
        "classification": "Conservative",
        "wickets_remaining_start": 10,
        "wickets_remaining_end": 10,
        "balls": 6
      },
      {
        "over": 2,
        "runs": 17,
        "wickets": 0,
        "run_rate": 17.0,
        "classification": "Attacking",
        "wickets_remaining_start": 10,
        "wickets_remaining_end": 10,
        "balls": 6
      },
      {
        "over": 3,
        "runs": 24,
        "wickets": 0,
        "run_rate": 24.0,
        "classification": "Attacking",
        "wickets_remaining_start": 10,
        "wickets_remaining_end": 10,
        "balls": 6
      },
      {
        "over": 4,
        "runs": 11,
        "wickets": 0,
        "run_rate": 11.0,
        "classification": "Attacking",
        "wickets_remaining_start": 10,
        "wickets_remaining_end": 10,
        "balls": 6
      },
      {
        "over": 5,
        "runs": 10,
        "wickets": 1,
        "run_rate": 10.0,
        "classification": "Efficient",
        "wickets_remaining_start": 10,
        "wickets_remaining_end": 9,
        "balls": 6
      },
      {
        "over": 6,
        "runs": 16,
        "wickets": 0,
        "run_rate": 16.0,
        "classification": "Attacking",
        "wickets_remaining_start": 9,
        "wickets_remaining_end": 9,
        "balls": 6
      },
      {
        "over": 7,
        "runs": 6,
        "wickets": 0,
        "run_rate": 6.0,
        "classification": "Conservative",
        "wickets_remaining_start": 9,
        "wickets_remaining_end": 9,
        "balls": 6
      },
      {
        "over": 8,
        "runs": 9,
        "wickets": 1,
        "run_rate": 9.0,
        "classification": "Efficient",
        "wickets_remaining_start": 9,
        "wickets_remaining_end": 8,
        "balls": 6
      },
      {
        "over": 9,
        "runs": 10,
        "wickets": 0,
        "run_rate": 10.0,
        "classification": "Efficient",
        "wickets_remaining_start": 8,
        "wickets_remaining_end": 8,
        "balls": 6
      },
      {
        "over": 10,
        "runs": 10,
        "wickets": 0,
        "run_rate": 10.0,
        "classification": "Efficient",
        "wickets_remaining_start": 8,
        "wickets_remaining_end": 8,
        "balls": 6
      },
      {
        "over": 11,
        "runs": 5,
        "wickets": 0,
        "run_rate": 5.0,
        "classification": "Conservative",
        "wickets_remaining_start": 8,
        "wickets_remaining_end": 8,
        "balls": 6
      },
      {
        "over": 12,
        "runs": 8,
        "wickets": 0,
        "run_rate": 8.0,
        "classification": "Efficient",
        "wickets_remaining_start": 8,
        "wickets_remaining_end": 8,
        "balls": 6
      },
      {
        "over": 13,
        "runs": 6,
        "wickets": 1,
        "run_rate": 6.0,
        "classification": "Efficient",
        "wickets_remaining_start": 8,
        "wickets_remaining_end": 7,
        "balls": 6
      },
      {
        "over": 14,
        "runs": 17,
        "wickets": 0,
        "run_rate": 17.0,
        "classification": "Attacking",
        "wickets_remaining_start": 7,
        "wickets_remaining_end": 7,
        "balls": 6
      },
      {
        "over": 15,
        "runs": 9,
        "wickets": 0,
        "run_rate": 9.0,
        "classification": "Efficient",
        "wickets_remaining_start": 7,
        "wickets_remaining_end": 7,
        "balls": 6
      },
      {
        "over": 16,
        "runs": 14,
        "wickets": 0,
        "run_rate": 14.0,
        "classification": "Attacking",
        "wickets_remaining_start": 7,
        "wickets_remaining_end": 7,
        "balls": 6
      },
      {
        "over": 17,
        "runs": 8,
        "wickets": 0,
        "run_rate": 8.0,
        "classification": "Efficient",
        "wickets_remaining_start": 7,
        "wickets_remaining_end": 7,
        "balls": 6
      },
      {
        "over": 18,
        "runs": 9,
        "wickets": 1,
        "run_rate": 9.0,
        "classification": "Efficient",
        "wickets_remaining_start": 7,
        "wickets_remaining_end": 6,
        "balls": 6
      },
      {
        "over": 19,
        "runs": 9,
        "wickets": 0,
        "run_rate": 9.0,
        "classification": "Efficient",
        "wickets_remaining_start": 6,
        "wickets_remaining_end": 6,
        "balls": 6
      }
    ],
    "innings2": [
      {
        "over": 0,
        "runs": 5,
        "wickets": 0,
        "run_rate": 5.0,
        "classification": "Conservative",
        "wickets_remaining_start": 10,
        "wickets_remaining_end": 10,
        "balls": 6
      },
      {
        "over": 1,
        "runs": 9,
        "wickets": 0,
        "run_rate": 9.0,
        "classification": "Efficient",
        "wickets_remaining_start": 10,
        "wickets_remaining_end": 10,
        "balls": 6
      },
      {
        "over": 2,
        "runs": 19,
        "wickets": 0,
        "run_rate": 19.0,
        "classification": "Attacking",
        "wickets_remaining_start": 10,
        "wickets_remaining_end": 10,
        "balls": 6
      },
      {
        "over": 3,
        "runs": 15,
        "wickets": 0,
        "run_rate": 15.0,
        "classification": "Attacking",
        "wickets_remaining_start": 10,
        "wickets_remaining_end": 10,
        "balls": 6
      },
      {
        "over": 4,
        "runs": 15,
        "wickets": 0,
        "run_rate": 15.0,
        "classification": "Attacking",
        "wickets_remaining_start": 10,
        "wickets_remaining_end": 10,
        "balls": 6
      },
      {
        "over": 5,
        "runs": 16,
        "wickets": 0,
        "run_rate": 16.0,
        "classification": "Attacking",
        "wickets_remaining_start": 10,
        "wickets_remaining_end": 10,
        "balls": 6
      },
      {
        "over": 6,
        "runs": 8,
        "wickets": 0,
        "run_rate": 8.0,
        "classification": "Efficient",
        "wickets_remaining_start": 10,
        "wickets_remaining_end": 10,
        "balls": 6
      },
      {
        "over": 7,
        "runs": 8,
        "wickets": 0,
        "run_rate": 8.0,
        "classification": "Efficient",
        "wickets_remaining_start": 10,
        "wickets_remaining_end": 10,
        "balls": 6
      },
      {
        "over": 8,
        "runs": 14,
        "wickets": 0,
        "run_rate": 14.0,
        "classification": "Attacking",
        "wickets_remaining_start": 10,
        "wickets_remaining_end": 10,
        "balls": 6
      },
      {
        "over": 9,
        "runs": 10,
        "wickets": 0,
        "run_rate": 10.0,
        "classification": "Efficient",
        "wickets_remaining_start": 10,
        "wickets_remaining_end": 10,
        "balls": 6
      },
      {
        "over": 10,
        "runs": 13,
        "wickets": 0,
        "run_rate": 13.0,
        "classification": "Attacking",
        "wickets_remaining_start": 10,
        "wickets_remaining_end": 10,
        "balls": 6
      },
      {
        "over": 11,
        "runs": 16,
        "wickets": 1,
        "run_rate": 16.0,
        "classification": "Attacking",
        "wickets_remaining_start": 10,
        "wickets_remaining_end": 9,
        "balls": 6
      },
      {
        "over": 12,
        "runs": 10,
        "wickets": 0,
        "run_rate": 10.0,
        "classification": "Efficient",
        "wickets_remaining_start": 9,
        "wickets_remaining_end": 9,
        "balls": 6
      },
      {
        "over": 13,
        "runs": 11,
        "wickets": 0,
        "run_rate": 11.0,
        "classification": "Attacking",
        "wickets_remaining_start": 9,
        "wickets_remaining_end": 9,
        "balls": 6
      },
      {
        "over": 14,
        "runs": 8,
        "wickets": 1,
        "run_rate": 8.0,
        "classification": "Efficient",
        "wickets_remaining_start": 9,
        "wickets_remaining_end": 8,
        "balls": 6
      },
      {
        "over": 15,
        "runs": 9,
        "wickets": 1,
        "run_rate": 9.0,
        "classification": "Efficient",
        "wickets_remaining_start": 8,
        "wickets_remaining_end": 7,
        "balls": 6
      },
      {
        "over": 16,
        "runs": 7,
        "wickets": 0,
        "run_rate": 7.0,
        "classification": "Efficient",
        "wickets_remaining_start": 7,
        "wickets_remaining_end": 7,
        "balls": 6
      },
      {
        "over": 17,
        "runs": 11,
        "wickets": 0,
        "run_rate": 11.0,
        "classification": "Attacking",
        "wickets_remaining_start": 7,
        "wickets_remaining_end": 7,
        "balls": 6
      },
      {
        "over": 18,
        "runs": 8,
        "wickets": 1,
        "run_rate": 8.0,
        "classification": "Efficient",
        "wickets_remaining_start": 7,
        "wickets_remaining_end": 6,
        "balls": 6
      },
      {
        "over": 19,
        "runs": 4,
        "wickets": 0,
        "run_rate": 24.0,
        "classification": "Attacking",
        "wickets_remaining_start": 6,
        "wickets_remaining_end": 6,
        "balls": 1
      }
    ]
  },
  "matchups": {
    "innings1_matchups": [
      {
        "batsman": "Ajinkya Rahane",
        "bowler": "Shardul Thakur",
        "balls": 19,
        "runs": 28,
        "matchup_sr": 147.4,
        "overall_sr": 167.5,
        "wickets": 1,
        "effectiveness": "effective",
        "verdict": "Thakur dominated Rahane \u2014 held him below his season average SR"
      },
      {
        "batsman": "Finn Allen",
        "bowler": "Shardul Thakur",
        "balls": 8,
        "runs": 12,
        "matchup_sr": 150.0,
        "overall_sr": 217.6,
        "wickets": 1,
        "effectiveness": "effective",
        "verdict": "Allen's SR crashed against Thakur \u2014 the slower ball was unplayable"
      },
      {
        "batsman": "Angkrish Raghuvanshi",
        "bowler": "Jasprit Bumrah",
        "balls": 10,
        "runs": 14,
        "matchup_sr": 140.0,
        "overall_sr": 175.9,
        "wickets": 0,
        "effectiveness": "effective",
        "verdict": "Bumrah contained Raghuvanshi to 140 SR \u2014 36 below his innings average"
      },
      {
        "batsman": "Rinku Singh",
        "bowler": "AM Ghazanfar",
        "balls": 8,
        "runs": 18,
        "matchup_sr": 225.0,
        "overall_sr": 157.1,
        "wickets": 0,
        "effectiveness": "ineffective",
        "verdict": "Rinku punished Ghazanfar \u2014 225 SR against the spinner was his best passage"
      }
    ],
    "innings2_matchups": [
      {
        "batsman": "Rohit Sharma",
        "bowler": "Vaibhav Arora",
        "balls": 12,
        "runs": 28,
        "matchup_sr": 233.3,
        "overall_sr": 205.3,
        "wickets": 1,
        "effectiveness": "ineffective",
        "verdict": "Rohit absolutely feasted on Arora before the dismissal \u2014 233 SR"
      },
      {
        "batsman": "Ryan Rickelton",
        "bowler": "Varun Chakravarthy",
        "balls": 14,
        "runs": 22,
        "matchup_sr": 157.1,
        "overall_sr": 188.4,
        "wickets": 0,
        "effectiveness": "effective",
        "verdict": "Chakravarthy was KKR's best option vs Rickelton \u2014 held him 31 below average"
      },
      {
        "batsman": "Rohit Sharma",
        "bowler": "Sunil Narine",
        "balls": 8,
        "runs": 22,
        "matchup_sr": 275.0,
        "overall_sr": 205.3,
        "wickets": 0,
        "effectiveness": "ineffective",
        "verdict": "Narine had no answer for Rohit \u2014 275 SR against the off-spinner"
      }
    ]
  },
  "partnerships": {
    "innings1": [
      {
        "batsman1": "Finn Allen",
        "batsman2": "Ajinkya Rahane",
        "runs": 69,
        "balls": 31,
        "sr": 222.6,
        "start_over": 0.0,
        "end_over": 5.2,
        "load_bearing": false
      },
      {
        "batsman1": "Cameron Green",
        "batsman2": "Ajinkya Rahane",
        "runs": 40,
        "balls": 22,
        "sr": 181.8,
        "start_over": 5.2,
        "end_over": 8.5,
        "load_bearing": false
      },
      {
        "batsman1": "Angkrish Raghuvanshi",
        "batsman2": "Ajinkya Rahane",
        "runs": 36,
        "balls": 21,
        "sr": 171.4,
        "start_over": 8.5,
        "end_over": 13.3,
        "load_bearing": false
      },
      {
        "batsman1": "Angkrish Raghuvanshi",
        "batsman2": "Rinku Singh",
        "runs": 60,
        "balls": 29,
        "sr": 206.9,
        "start_over": 13.3,
        "end_over": 18.3,
        "load_bearing": true
      },
      {
        "batsman1": "Rinku Singh",
        "batsman2": "Ramandeep Singh",
        "runs": 15,
        "balls": 9,
        "sr": 166.7,
        "start_over": 18.3,
        "end_over": 20.0,
        "load_bearing": false
      }
    ],
    "innings2": [
      {
        "batsman1": "Ryan Rickelton",
        "batsman2": "Rohit Sharma",
        "runs": 148,
        "balls": 71,
        "sr": 208.5,
        "start_over": 0.0,
        "end_over": 11.5,
        "load_bearing": true
      },
      {
        "batsman1": "Ryan Rickelton",
        "batsman2": "Suryakumar Yadav",
        "runs": 31,
        "balls": 15,
        "sr": 206.7,
        "start_over": 11.5,
        "end_over": 14.2,
        "load_bearing": false
      },
      {
        "batsman1": "Ryan Rickelton",
        "batsman2": "Tilak Varma",
        "runs": 5,
        "balls": 6,
        "sr": 83.3,
        "start_over": 14.2,
        "end_over": 15.2,
        "load_bearing": false
      },
      {
        "batsman1": "Tilak Varma",
        "batsman2": "Hardik Pandya",
        "runs": 31,
        "balls": 20,
        "sr": 155.0,
        "start_over": 15.2,
        "end_over": 18.4,
        "load_bearing": false
      },
      {
        "batsman1": "Hardik Pandya",
        "batsman2": "Naman Dhir",
        "runs": 9,
        "balls": 5,
        "sr": 180.0,
        "start_over": 18.4,
        "end_over": 19.1,
        "load_bearing": false
      }
    ]
  },
  "turning_points": [
    {
      "id": 1,
      "label": "Turning Point 1: The Thakur Triple",
      "over_range": "5-13",
      "description": "Shardul Thakur's three wickets in four overs (Allen at 5.2, Green at 8.5, Rahane at 13.3) dismantled KKR's platform. At 69/0 after 5.2 overs, KKR were on track for 230+. Thakur's first over changed the trajectory completely.",
      "wp_before": 0.5,
      "wp_after": 0.62,
      "pressure_shift": "High \u2192 Extreme"
    },
    {
      "id": 2,
      "label": "Turning Point 2: The Rickelton-Rohit Blitz",
      "over_range": "1-12",
      "description": "MI's opening stand of 148 from 71 balls. By over 6, MI had 80/0 chasing 221. The KKR bowling attack had no answer. Rickelton hit 8 sixes; Rohit was at 50 off 23 balls.",
      "wp_before": 0.48,
      "wp_after": 0.78,
      "pressure_shift": "Normal \u2192 Low"
    },
    {
      "id": 3,
      "label": "Turning Point 3: Wickets in Overs 14-15",
      "over_range": "14-15",
      "description": "MI lost Suryakumar (14.2) and Rickelton (15.2) in consecutive overs, going from 179/1 to 184/3. KKR sensed a chance \u2014 but MI still only needed 37 from 5 overs with 7 wickets in hand. The game was never truly in doubt again.",
      "wp_before": 0.82,
      "wp_after": 0.71,
      "pressure_shift": "Low \u2192 Moderate"
    }
  ],
  "counterfactual_scenarios": [
    {
      "scenario_id": 1,
      "title": "What If Shardul Thakur Had Bowled Average?",
      "change": "Replace Thakur's 3/39 with an average IPL death/middle-overs spell of 0/48 (economy 12)",
      "original_outcome": "KKR 220/4 in 20 overs",
      "lola_outcome": "KKR ~237/1 in 20 overs \u2014 target 238",
      "key_number": 17,
      "original_win_prob": 0.22,
      "counterfactual_win_prob": 0.12,
      "narrative": "Shardul Thakur's first over wasn't supposed to happen like that. An average IPL replacement across those same four overs \u2014 bowling at 12 RPO and taking no wickets \u2014 adds roughly 17 extra runs and preserves all three dismissed batsmen. Finn Allen, playing at 217.64 SR when dismissed at 5.2, was just warming up. Cameron Green, caught miscuing off a pace-variation at 180 SR, had another 10 overs of batting left in him.\n\nIn the counterfactual, KKR reach the drinks break at 13 overs with Rahane still at the crease and 145/0 on the board. The Rahane-Raghuvanshi partnership that was worth 36 in reality becomes worth 60+, as Rahane no longer faces a scoring-rate imperative. With the keeper and batter cycling freely, KKR close at 237 or 238 \u2014 a target MI's top order could not have absorbed without a perfect powerplay.\n\nThe numbers quantify what the eye suspected: Thakur's three-wicket haul wasn't just match-altering, it was match-defining. Take it away, and you're looking at a 17-run swing and a KKR victory built on platform cricket rather than the collapse narrative we witnessed."
    },
    {
      "scenario_id": 2,
      "title": "What If Rohit Sharma Had Been Run Out at 50?",
      "change": "Remove Rohit Sharma's 78-run contribution after ball 23 (when he reached 50). He scores 52 before being run out, batting 23 balls total.",
      "original_outcome": "MI 224/4 in 19.1 overs \u2014 won by 6 wickets",
      "lola_outcome": "MI 195/5 in 19.1 overs \u2014 lost by 25 runs (counterfactual target 221)",
      "key_number": 26,
      "original_win_prob": 0.92,
      "counterfactual_win_prob": 0.35,
      "narrative": "Rohit Sharma at his best in T20 cricket doesn't just score runs \u2014 he reframes the asking rate so aggressively that opposition bowlers lose their plans. By the end of over 6, Rohit was on 51 off 23 balls. The 50% win probability that existed at the toss had already blown out to 75% for MI.\n\nImagine instead a run-out at that exact moment \u2014 a direct hit from Anukul Roy that didn't bounce off his knee guard in reality. Rohit departs for 52. MI are 100/1 at over 8, with Rickelton still batting (he hit all 8 of his sixes regardless). But now the asking rate is 9.3 from 12 overs, not the 6.5 it was in reality.\n\nThe Rickelton run-out that followed in reality came when MI were 184 chasing 221 with enormous cushion. In our scenario, it comes when MI are 160 and need 61 off 7 overs \u2014 a coin-flip requiring clean hitting rather than clinical execution. KKR win by 25 runs in a match where one direct hit changed everything. This is why Rohit's powerplay isn't just an aesthetic pleasure \u2014 it's structural insurance."
    }
  ],
  "commentary_gems": [
    {
      "over_ball": "5.2",
      "text": "lord strikes! Allen looks to go downtown but ends up dragging this slower delivery to wide long-on. KKR were running away with it, so this is a big wicket. That was bowled at 117kph.",
      "context": "Shardul Thakur's first wicket \u2014 the turning point of KKR's innings"
    },
    {
      "over_ball": "13.3",
      "text": "Shardul Thakur can do no wrong today! Three overs, three wickets! Rahane falls with the pressure building. Cross-seam full ball outside off.",
      "context": "Completing the Thakur hat-trick of wickets"
    },
    {
      "over_ball": "11.5",
      "text": "Anukul Roy hangs on to a clanger! He has a habit of those! 137kph full ball angled across, Rohit looks to slog it away but it comes off the top edge.",
      "context": "Rohit's dismissal \u2014 the catch nobody expected Roy to hold"
    },
    {
      "over_ball": "18.6",
      "text": "Finds the gap! Hardik Pandya levels the scores as he takes on this half-tracker. Pulls it away wide of long-off, and MI are one run away",
      "context": "The penultimate ball \u2014 MI needed 2 off 2"
    },
    {
      "over_ball": "19.1",
      "text": "And Mumbai Indians win their first season-opener since 2012! And they do it by pulling off their biggest chase!",
      "context": "The winning moment \u2014 Roy to Naman Dhir, FOUR"
    }
  ],
  "game_changers": [
    {
      "name": "Shardul Thakur",
      "team": "MI",
      "key_stat": "4-0-39-3 | 3 wickets across overs 5, 8 and 13",
      "contribution": "Thakur's three wickets transformed a KKR innings that was cruising at 69/0 after 5.2 overs into a 220-all-out. At 217.64 SR, Finn Allen was batting in another gear \u2014 the dismissal at 5.2 changed the match's centre of gravity entirely. Player of the Match, and correctly so."
    },
    {
      "name": "Rohit Sharma",
      "team": "MI",
      "key_stat": "78 off 38 balls | SR 205.26 | 6 fours, 6 sixes",
      "contribution": "Rohit's 78 off 38 in the powerplay dismantled the chase before it began. KKR's bowlers had no answer. By over 6, MI were 80/0 and the required rate had dropped below 10. The innings wasn't won in the last over \u2014 it was won in the first six."
    },
    {
      "name": "Ryan Rickelton",
      "team": "MI",
      "key_stat": "81 off 43 balls | SR 188.37 | 8 sixes",
      "contribution": "Eight sixes from the wicketkeeper-batter announced an IPL career with force. Rickelton's contribution at the other end of the Rohit stand wasn't just runs \u2014 it was sustained pressure on every bowler. His run-out at 184 was the only moment KKR could celebrate."
    },
    {
      "name": "Angkrish Raghuvanshi",
      "team": "KKR",
      "key_stat": "51 off 29 balls | SR 175.86 | 6 fours, 2 sixes",
      "contribution": "From the losing side: Raghuvanshi's 51 off 29 in the death overs is the reason KKR posted 220 rather than 190. After Rahane fell at 145/3 in over 13, Raghuvanshi absorbed the pressure and then detonated \u2014 50 runs in the last 5 overs with Rinku alongside him."
    }
  ]
}