[
  {
    "over": 0,
    "ball": 1,
    "batsman": "Salt",
    "non_striker": "",
    "bowler": "Khaleel Ahmed",
    "runs_off_bat": 0,
    "extras": 0,
    "extra_type": null,
    "wicket": false,
    "wicket_type": null,
    "fielder": null,
    "commentary_text": "fullish on middle and leg. A bit of shape away and Salt comes forward to push it to mid on",
    "cumulative_score": 0,
    "cumulative_wickets": 0,
    "is_boundary_four": false,
    "is_boundary_six": false,
    "is_dot": true
  },
  {
    "over": 0,
    "ball": 2,
    "batsman": "Salt",
    "non_striker": "",
    "bowler": "Khaleel Ahmed",
    "runs_off_bat": 0,
    "extras": 0,
    "extra_type": null,
    "wicket": false,
    "wicket_type": null,
    "fielder": null,
    "commentary_text": "back of a length outside off and this moves away late. Salt goes wafting at it without much foot movement and is beaten on the outside",
    "cumulative_score": 0,
    "cumulative_wickets": 0,
    "is_boundary_four": false,
    "is_boundary_six": false,
    "is_dot": true
  },
  {
    "over": 0,
    "ball": 3,
    "batsman": "Salt",
    "non_striker": "",
    "bowler": "Khaleel Ahmed",
    "runs_off_bat": 3,
    "extras": 0,
    "extra_type": null,
    "wicket": false,
    "wicket_type": null,
    "fielder": null,
    "commentary_text": "full and wide outside off. Salt throws his hands at it and slices it over point. The ball plugs in the outfield and Henry, running around from deep backward point, cuts it off",
    "cumulative_score": 3,
    "cumulative_wickets": 0,
    "is_boundary_four": false,
    "is_boundary_six": false,
    "is_dot": false
  },
  {
    "over": 0,
    "ball": 4,
    "batsman": "Kohli",
    "non_striker": "",
    "bowler": "Khaleel Ahmed",
    "runs_off_bat": 0,
    "extras": 0,
    "extra_type": null,
    "wicket": false,
    "wicket_type": null,
    "fielder": null,
    "commentary_text": "a direct hit and Kohli might have been walking back for a golden duck! Back of a length on off. Kohli tips it to point and calls for the single. Gets sent back from half-way and Veer's throw is just off the mark. Early reprieve for Kohli!",
    "cumulative_score": 3,
    "cumulative_wickets": 0,
    "is_boundary_four": false,
    "is_boundary_six": false,
    "is_dot": true
  },
  {
    "over": 0,
    "ball": 5,
    "batsman": "Kohli",
    "non_striker": "",
    "bowler": "Khaleel Ahmed",
    "runs_off_bat": 2,
    "extras": 0,
    "extra_type": null,
    "wicket": false,
    "wicket_type": null,
    "fielder": null,
    "commentary_text": "Full on middle and off. Stops a little in the surface and Kohli is early on his lofted stroke. Just enough legs to clear Dube at mid on, though",
    "cumulative_score": 5,
    "cumulative_wickets": 0,
    "is_boundary_four": false,
    "is_boundary_six": false,
    "is_dot": false
  },
  {
    "over": 0,
    "ball": 6,
    "batsman": "Kohli",
    "non_striker": "",
    "bowler": "Khaleel Ahmed",
    "runs_off_bat": 0,
    "extras": 0,
    "extra_type": null,
    "wicket": false,
    "wicket_type": null,
    "fielder": null,
    "commentary_text": "length ball pushed across the batter outside off. Kohli goes chasing after it and only connects with fresh air",
    "cumulative_score": 5,
    "cumulative_wickets": 0,
    "is_boundary_four": false,
    "is_boundary_six": false,
    "is_dot": true
  },
  {
    "over": 1,
    "ball": 1,
    "batsman": "Salt",
    "non_striker": "",
    "bowler": "Henry",
    "runs_off_bat": 1,
    "extras": 0,
    "extra_type": null,
    "wicket": false,
    "wicket_type": null,
    "fielder": null,
    "commentary_text": "back of a length outside off. Salt gets up on his toes and runs it down to short third, where Khaleel misfields and ends up conceding a single",
    "cumulative_score": 6,
    "cumulative_wickets": 0,
    "is_boundary_four": false,
    "is_boundary_six": false,
    "is_dot": false
  },
  {
    "over": 1,
    "ball": 2,
    "batsman": "Kohli",
    "non_striker": "",
    "bowler": "Henry",
    "runs_off_bat": 1,
    "extras": 0,
    "extra_type": null,
    "wicket": false,
    "wicket_type": null,
    "fielder": null,
    "commentary_text": "back of a length just outside off. Kohli dabs it to short third and Khaleel misfields yet again. No extra runs conceded this time, though",
    "cumulative_score": 7,
    "cumulative_wickets": 0,
    "is_boundary_four": false,
    "is_boundary_six": false,
    "is_dot": false
  },
  {
    "over": 1,
    "ball": 3,
    "batsman": "Salt",
    "non_striker": "",
    "bowler": "Henry",
    "runs_off_bat": 1,
    "extras": 0,
    "extra_type": null,
    "wicket": false,
    "wicket_type": null,
    "fielder": null,
    "commentary_text": "Fullish outside off and this leaves the batter a touch. Salt throws his hands at it and slices it down to deep backward point",
    "cumulative_score": 8,
    "cumulative_wickets": 0,
    "is_boundary_four": false,
    "is_boundary_six": false,
    "is_dot": false
  },
  {
    "over": 1,
    "ball": 4,
    "batsman": "Kohli",
    "non_striker": "",
    "bowler": "Henry",
    "runs_off_bat": 2,
    "extras": 0,
    "extra_type": null,
    "wicket": false,
    "wicket_type": null,
    "fielder": null,
    "commentary_text": "Marginally short outside off. Kohli stands up tall and whips a pull towards deep square, where Noor sprawls to his left and saves two",
    "cumulative_score": 10,
    "cumulative_wickets": 0,
    "is_boundary_four": false,
    "is_boundary_six": false,
    "is_dot": false
  },
  {
    "over": 1,
    "ball": 5,
    "batsman": "Kohli",
    "non_striker": "",
    "bowler": "Henry",
    "runs_off_bat": 1,
    "extras": 0,
    "extra_type": null,
    "wicket": false,
    "wicket_type": null,
    "fielder": null,
    "commentary_text": "hard length outside off. Kohli charges down the track before shanking it to mid on",
    "cumulative_score": 11,
    "cumulative_wickets": 0,
    "is_boundary_four": false,
    "is_boundary_six": false,
    "is_dot": false
  },
  {
    "over": 1,
    "ball": 6,
    "batsman": "Salt",
    "non_striker": "",
    "bowler": "Henry",
    "runs_off_bat": 0,
    "extras": 0,
    "extra_type": null,
    "wicket": false,
    "wicket_type": null,
    "fielder": null,
    "commentary_text": "length ball outside off. Salt plants his front foot and drills it straight to mid off",
    "cumulative_score": 11,
    "cumulative_wickets": 0,
    "is_boundary_four": false,
    "is_boundary_six": false,
    "is_dot": true
  },
  {
    "over": 2,
    "ball": 1,
    "batsman": "Kohli",
    "non_striker": "",
    "bowler": "Khaleel Ahmed",
    "runs_off_bat": 1,
    "extras": 0,
    "extra_type": null,
    "wicket": false,
    "wicket_type": null,
    "fielder": null,
    "commentary_text": "banged in short outside off and this comes off a touch sluggishly. Kohli tugs it enough to mid wicket's right and settles for a single",
    "cumulative_score": 12,
    "cumulative_wickets": 0,
    "is_boundary_four": false,
    "is_boundary_six": false,
    "is_dot": false
  },
  {
    "over": 2,
    "ball": 2,
    "batsman": "Salt",
    "non_striker": "",
    "bowler": "Khaleel Ahmed",
    "runs_off_bat": 1,
    "extras": 0,
    "extra_type": null,
    "wicket": false,
    "wicket_type": null,
    "fielder": null,
    "commentary_text": "back of a length outside off. Salt tries the fight the angle away from him and slices it towards deep backward point",
    "cumulative_score": 13,
    "cumulative_wickets": 0,
    "is_boundary_four": false,
    "is_boundary_six": false,
    "is_dot": false
  },
  {
    "over": 2,
    "ball": 3,
    "batsman": "Kohli",
    "non_striker": "",
    "bowler": "Khaleel Ahmed",
    "runs_off_bat": 2,
    "extras": 0,
    "extra_type": null,
    "wicket": false,
    "wicket_type": null,
    "fielder": null,
    "commentary_text": "goes straight up, and Dube puts it down! Kohli breathes a sigh of relief! Hard length just outside off. Kohli has a hack at it and shanks it badly. Dube runs back from mid on, gets under it but the ball hits his hands and then his chest. Not a moment Dube will want to look back on again!",
    "cumulative_score": 15,
    "cumulative_wickets": 0,
    "is_boundary_four": false,
    "is_boundary_six": false,
    "is_dot": false
  },
  {
    "over": 2,
    "ball": 4,
    "batsman": "Kohli",
    "non_striker": "",
    "bowler": "Khaleel Ahmed",
    "runs_off_bat": 0,
    "extras": 1,
    "extra_type": "legbye",
    "wicket": false,
    "wicket_type": null,
    "fielder": null,
    "commentary_text": "length ball shaping into the pads. Kohli has another swipe at it and seems to miss, with the ball rolling off the pad behind square",
    "cumulative_score": 16,
    "cumulative_wickets": 0,
    "is_boundary_four": false,
    "is_boundary_six": false,
    "is_dot": false
  },
  {
    "over": 2,
    "ball": 5,
    "batsman": "Salt",
    "non_striker": "",
    "bowler": "Khaleel Ahmed",
    "runs_off_bat": 1,
    "extras": 0,
    "extra_type": null,
    "wicket": false,
    "wicket_type": null,
    "fielder": null,
    "commentary_text": "off-pace on a back of a length outside off. Salt waits for it and slaps it to mid off before scampering across to the other end",
    "cumulative_score": 17,
    "cumulative_wickets": 0,
    "is_boundary_four": false,
    "is_boundary_six": false,
    "is_dot": false
  },
  {
    "over": 2,
    "ball": 6,
    "batsman": "Kohli",
    "non_striker": "",
    "bowler": "Khaleel Ahmed",
    "runs_off_bat": 0,
    "extras": 0,
    "extra_type": null,
    "wicket": false,
    "wicket_type": null,
    "fielder": null,
    "commentary_text": "length ball slanted across the batter outside off. Kohli has a wild swish at it and misses the ball by a fair distance. An un-Kohli-esque shot",
    "cumulative_score": 17,
    "cumulative_wickets": 0,
    "is_boundary_four": false,
    "is_boundary_six": false,
    "is_dot": true
  },
  {
    "over": 3,
    "ball": 1,
    "batsman": "Salt",
    "non_striker": "",
    "bowler": "Henry",
    "runs_off_bat": 1,
    "extras": 0,
    "extra_type": null,
    "wicket": false,
    "wicket_type": null,
    "fielder": null,
    "commentary_text": "over the top but this plugs too! Full just outside off. Salt gets under it and muscles it over mid on. The ball just stops in the surface after pitching and Dube can retrieve it!",
    "cumulative_score": 18,
    "cumulative_wickets": 0,
    "is_boundary_four": false,
    "is_boundary_six": false,
    "is_dot": false
  },
  {
    "over": 3,
    "ball": 2,
    "batsman": "Kohli",
    "non_striker": "",
    "bowler": "Henry",
    "runs_off_bat": 6,
    "extras": 0,
    "extra_type": null,
    "wicket": false,
    "wicket_type": null,
    "fielder": null,
    "commentary_text": "pick the bones out of that one! And it is a no-look six to boot. On a length just outside off. Kohli plants his front foot and whips it over mid wicket!",
    "cumulative_score": 24,
    "cumulative_wickets": 0,
    "is_boundary_four": false,
    "is_boundary_six": true,
    "is_dot": false
  },
  {
    "over": 3,
    "ball": 3,
    "batsman": "Kohli",
    "non_striker": "",
    "bowler": "Henry",
    "runs_off_bat": 2,
    "extras": 0,
    "extra_type": null,
    "wicket": false,
    "wicket_type": null,
    "fielder": null,
    "commentary_text": "full just outside off. Kohli plants his front foot again and scuffs it over the bowler's head. Back for a brace",
    "cumulative_score": 26,
    "cumulative_wickets": 0,
    "is_boundary_four": false,
    "is_boundary_six": false,
    "is_dot": false
  },
  {
    "over": 3,
    "ball": 4,
    "batsman": "Kohli",
    "non_striker": "",
    "bowler": "Henry",
    "runs_off_bat": 2,
    "extras": 0,
    "extra_type": null,
    "wicket": false,
    "wicket_type": null,
    "fielder": null,
    "commentary_text": "dug in and following the batter outside leg. Kohli, having advanced, short-arm-jabs it behind square for a couple of runs",
    "cumulative_score": 28,
    "cumulative_wickets": 0,
    "is_boundary_four": false,
    "is_boundary_six": false,
    "is_dot": false
  },
  {
    "over": 3,
    "ball": 5,
    "batsman": "Kohli",
    "non_striker": "",
    "bowler": "Henry",
    "runs_off_bat": 4,
    "extras": 0,
    "extra_type": null,
    "wicket": false,
    "wicket_type": null,
    "fielder": null,
    "commentary_text": "Full just outside off. Kohli marches down the track, shows the full face of the bat and cracks it back past the bowler!",
    "cumulative_score": 32,
    "cumulative_wickets": 0,
    "is_boundary_four": true,
    "is_boundary_six": false,
    "is_dot": false
  },
  {
    "over": 3,
    "ball": 6,
    "batsman": "Kohli",
    "non_striker": "",
    "bowler": "Henry",
    "runs_off_bat": 1,
    "extras": 0,
    "extra_type": null,
    "wicket": false,
    "wicket_type": null,
    "fielder": null,
    "commentary_text": "back of a length on off. Kohli drops it into the mid wicket region and keeps strike",
    "cumulative_score": 33,
    "cumulative_wickets": 0,
    "is_boundary_four": false,
    "is_boundary_six": false,
    "is_dot": false
  },
  {
    "over": 4,
    "ball": 1,
    "batsman": "Kohli",
    "non_striker": "",
    "bowler": "Kamboj",
    "runs_off_bat": 0,
    "extras": 0,
    "extra_type": null,
    "wicket": false,
    "wicket_type": null,
    "fielder": null,
    "commentary_text": "back of a length outside off. Kohli skips down the track and shanks it on the bounce to mid off. That seemed to stick in the surface too",
    "cumulative_score": 33,
    "cumulative_wickets": 0,
    "is_boundary_four": false,
    "is_boundary_six": false,
    "is_dot": true
  },
  {
    "over": 4,
    "ball": 2,
    "batsman": "Kohli",
    "non_striker": "",
    "bowler": "Kamboj",
    "runs_off_bat": 4,
    "extras": 0,
    "extra_type": null,
    "wicket": false,
    "wicket_type": null,
    "fielder": null,
    "commentary_text": "Kohli continues on his merry way! Length ball just outside off. Kohli opens up his front hip and smears it over mid wicket!",
    "cumulative_score": 37,
    "cumulative_wickets": 0,
    "is_boundary_four": true,
    "is_boundary_six": false,
    "is_dot": false
  },
  {
    "over": 4,
    "ball": 3,
    "batsman": "Kohli",
    "non_striker": "",
    "bowler": "Kamboj",
    "runs_off_bat": 0,
    "extras": 0,
    "extra_type": null,
    "wicket": true,
    "wicket_type": "other",
    "fielder": null,
    "commentary_text": "bashed in short, and Kohli bites the dust! Dube with a bit of redemption! A little outside off. Kohli advances and tries to fetch it from outside the line. Gets a little under it and miscues it badly. Dube, stationed at long on, runs in and does the rest, despite the close proximity of Noor, who had run towards Dube from mid wicket. Kamboj with the breakthrough, and there is stunned silence at the Chinnaswamy!",
    "cumulative_score": 37,
    "cumulative_wickets": 1,
    "is_boundary_four": false,
    "is_boundary_six": false,
    "is_dot": false
  },
  {
    "over": 4,
    "ball": 4,
    "batsman": "Padikkal",
    "non_striker": "",
    "bowler": "Kamboj",
    "runs_off_bat": 1,
    "extras": 0,
    "extra_type": null,
    "wicket": false,
    "wicket_type": null,
    "fielder": null,
    "commentary_text": "back of a length just outside off. Padikkal has a stab at it and jams it off the inside edge into his pads. Rolls away for a single into the off side",
    "cumulative_score": 38,
    "cumulative_wickets": 1,
    "is_boundary_four": false,
    "is_boundary_six": false,
    "is_dot": false
  },
  {
    "over": 4,
    "ball": 5,
    "batsman": "Salt",
    "non_striker": "",
    "bowler": "Kamboj",
    "runs_off_bat": 4,
    "extras": 0,
    "extra_type": null,
    "wicket": false,
    "wicket_type": null,
    "fielder": null,
    "commentary_text": "nicked and just past a diving Samson! That flew off the bat. On a back of a length, honing into off. Salt wafts at it and gets a thick enough outside edge to beat the keeper to his right!",
    "cumulative_score": 42,
    "cumulative_wickets": 1,
    "is_boundary_four": true,
    "is_boundary_six": false,
    "is_dot": false
  },
  {
    "over": 4,
    "ball": 6,
    "batsman": "Salt",
    "non_striker": "",
    "bowler": "Kamboj",
    "runs_off_bat": 1,
    "extras": 0,
    "extra_type": null,
    "wicket": false,
    "wicket_type": null,
    "fielder": null,
    "commentary_text": "hard length, nipping into off. Salt, cramped for room, jams it into the cover region",
    "cumulative_score": 43,
    "cumulative_wickets": 1,
    "is_boundary_four": false,
    "is_boundary_six": false,
    "is_dot": false
  },
  {
    "over": 5,
    "ball": 1,
    "batsman": "Salt",
    "non_striker": "",
    "bowler": "Khaleel Ahmed",
    "runs_off_bat": 2,
    "extras": 0,
    "extra_type": null,
    "wicket": false,
    "wicket_type": null,
    "fielder": null,
    "commentary_text": "slower ball on a length just outside leg. Salt too early into it and heaves it behind square. Not enough juice on the stroke, though, and cut off quite easily",
    "cumulative_score": 45,
    "cumulative_wickets": 1,
    "is_boundary_four": false,
    "is_boundary_six": false,
    "is_dot": false
  },
  {
    "over": 5,
    "ball": 2,
    "batsman": "Salt",
    "non_striker": "",
    "bowler": "Khaleel Ahmed",
    "runs_off_bat": 0,
    "extras": 0,
    "extra_type": null,
    "wicket": false,
    "wicket_type": null,
    "fielder": null,
    "commentary_text": "shortish outside off. Salt gets up on his toes and jabs it towards extra cover",
    "cumulative_score": 45,
    "cumulative_wickets": 1,
    "is_boundary_four": false,
    "is_boundary_six": false,
    "is_dot": true
  },
  {
    "over": 5,
    "ball": 3,
    "batsman": "Salt",
    "non_striker": "",
    "bowler": "Khaleel Ahmed",
    "runs_off_bat": 1,
    "extras": 0,
    "extra_type": null,
    "wicket": false,
    "wicket_type": null,
    "fielder": null,
    "commentary_text": "back of a length on off. Salt goes deep into his crease before punching it to mid on. Another easy single",
    "cumulative_score": 46,
    "cumulative_wickets": 1,
    "is_boundary_four": false,
    "is_boundary_six": false,
    "is_dot": false
  },
  {
    "over": 5,
    "ball": 4,
    "batsman": "Padikkal",
    "non_striker": "",
    "bowler": "Khaleel Ahmed",
    "runs_off_bat": 0,
    "extras": 0,
    "extra_type": null,
    "wicket": false,
    "wicket_type": null,
    "fielder": null,
    "commentary_text": "length ball hung up outside off. Padikkal throws the kitchen sink at it but misses",
    "cumulative_score": 46,
    "cumulative_wickets": 1,
    "is_boundary_four": false,
    "is_boundary_six": false,
    "is_dot": true
  },
  {
    "over": 5,
    "ball": 5,
    "batsman": "Padikkal",
    "non_striker": "",
    "bowler": "Khaleel Ahmed",
    "runs_off_bat": 1,
    "extras": 0,
    "extra_type": null,
    "wicket": false,
    "wicket_type": null,
    "fielder": null,
    "commentary_text": "first run for Padikkal off Khaleel. Back of a length outside off. Padikkal stays back and scuffs it towards sweeper cover",
    "cumulative_score": 47,
    "cumulative_wickets": 1,
    "is_boundary_four": false,
    "is_boundary_six": false,
    "is_dot": false
  },
  {
    "over": 5,
    "ball": 6,
    "batsman": "Salt",
    "non_striker": "",
    "bowler": "Khaleel Ahmed",
    "runs_off_bat": 4,
    "extras": 0,
    "extra_type": null,
    "wicket": false,
    "wicket_type": null,
    "fielder": null,
    "commentary_text": "shot! Strong way to end the powerplay! Half-tracker outside off. Salt sits back, picks the length early and belts it to mid on's right!",
    "cumulative_score": 51,
    "cumulative_wickets": 1,
    "is_boundary_four": true,
    "is_boundary_six": false,
    "is_dot": false
  },
  {
    "over": 6,
    "ball": 1,
    "batsman": "Padikkal",
    "non_striker": "",
    "bowler": "Kamboj",
    "runs_off_bat": 1,
    "extras": 0,
    "extra_type": null,
    "wicket": false,
    "wicket_type": null,
    "fielder": null,
    "commentary_text": "shortish outside off. Padikkal gets on top of the bounce and jabs it towards deep point. A bit of hesitation on the second and Padikkal has to scramble to return to the bowler's end",
    "cumulative_score": 52,
    "cumulative_wickets": 1,
    "is_boundary_four": false,
    "is_boundary_six": false,
    "is_dot": false
  },
  {
    "over": 6,
    "ball": 2,
    "batsman": "Salt",
    "non_striker": "",
    "bowler": "Kamboj",
    "runs_off_bat": 0,
    "extras": 0,
    "extra_type": null,
    "wicket": false,
    "wicket_type": null,
    "fielder": null,
    "commentary_text": "shortish outside off and this sits up too. Salt hammers it but straight to extra cover. He will feel he missed out there",
    "cumulative_score": 52,
    "cumulative_wickets": 1,
    "is_boundary_four": false,
    "is_boundary_six": false,
    "is_dot": true
  },
  {
    "over": 6,
    "ball": 2,
    "batsman": "Salt",
    "non_striker": "",
    "bowler": "Kamboj",
    "runs_off_bat": 0,
    "extras": 1,
    "extra_type": "wide",
    "wicket": false,
    "wicket_type": null,
    "fielder": null,
    "commentary_text": "banged in short outside off and this sails past the batter. Salt lets it go and the umpire calls it a wide on height",
    "cumulative_score": 53,
    "cumulative_wickets": 1,
    "is_boundary_four": false,
    "is_boundary_six": false,
    "is_dot": false
  },
  {
    "over": 6,
    "ball": 3,
    "batsman": "Salt",
    "non_striker": "",
    "bowler": "Kamboj",
    "runs_off_bat": 6,
    "extras": 0,
    "extra_type": null,
    "wicket": false,
    "wicket_type": null,
    "fielder": null,
    "commentary_text": "Marginally short on middle and leg. Salt swivels inside the line and muscles it just over the deep backward square leg fence!",
    "cumulative_score": 59,
    "cumulative_wickets": 1,
    "is_boundary_four": false,
    "is_boundary_six": true,
    "is_dot": false
  },
  {
    "over": 6,
    "ball": 4,
    "batsman": "Salt",
    "non_striker": "",
    "bowler": "Kamboj",
    "runs_off_bat": 2,
    "extras": 0,
    "extra_type": null,
    "wicket": false,
    "wicket_type": null,
    "fielder": null,
    "commentary_text": "back of a length on off. Salt punches it to extra cover, where Ghosh, on as a sub, misfields and ends up conceding an extra run",
    "cumulative_score": 61,
    "cumulative_wickets": 1,
    "is_boundary_four": false,
    "is_boundary_six": false,
    "is_dot": false
  },
  {
    "over": 6,
    "ball": 5,
    "batsman": "Salt",
    "non_striker": "",
    "bowler": "Kamboj",
    "runs_off_bat": 4,
    "extras": 0,
    "extra_type": null,
    "wicket": false,
    "wicket_type": null,
    "fielder": null,
    "commentary_text": "Leg-cutter but way too short. Sits up on middle and off and Salt obliterates it to deep mid wicket's right!",
    "cumulative_score": 65,
    "cumulative_wickets": 1,
    "is_boundary_four": true,
    "is_boundary_six": false,
    "is_dot": false
  },
  {
    "over": 6,
    "ball": 6,
    "batsman": "Salt",
    "non_striker": "",
    "bowler": "Kamboj",
    "runs_off_bat": 1,
    "extras": 0,
    "extra_type": null,
    "wicket": false,
    "wicket_type": null,
    "fielder": null,
    "commentary_text": "hard length just outside off. Salt uses the pace and runs it down to deep third",
    "cumulative_score": 66,
    "cumulative_wickets": 1,
    "is_boundary_four": false,
    "is_boundary_six": false,
    "is_dot": false
  },
  {
    "over": 7,
    "ball": 1,
    "batsman": "Salt",
    "non_striker": "",
    "bowler": "Noor Ahmad",
    "runs_off_bat": 0,
    "extras": 0,
    "extra_type": null,
    "wicket": false,
    "wicket_type": null,
    "fielder": null,
    "commentary_text": "zipped in very full just outside leg. Salt swings so hard at it that he ends up on the deck. Misses his stroke, with the ball pinging into his pad",
    "cumulative_score": 66,
    "cumulative_wickets": 1,
    "is_boundary_four": false,
    "is_boundary_six": false,
    "is_dot": true
  },
  {
    "over": 7,
    "ball": 2,
    "batsman": "Salt",
    "non_striker": "",
    "bowler": "Noor Ahmad",
    "runs_off_bat": 1,
    "extras": 0,
    "extra_type": null,
    "wicket": false,
    "wicket_type": null,
    "fielder": null,
    "commentary_text": "googly on a back of a length just outside off. Salt chops it behind point and gets Padikkal on strike",
    "cumulative_score": 67,
    "cumulative_wickets": 1,
    "is_boundary_four": false,
    "is_boundary_six": false,
    "is_dot": false
  },
  {
    "over": 7,
    "ball": 3,
    "batsman": "Padikkal",
    "non_striker": "",
    "bowler": "Noor Ahmad",
    "runs_off_bat": 1,
    "extras": 0,
    "extra_type": null,
    "wicket": false,
    "wicket_type": null,
    "fielder": null,
    "commentary_text": "length ball on middle and off. Padikkal goes back and knocks it to long on",
    "cumulative_score": 68,
    "cumulative_wickets": 1,
    "is_boundary_four": false,
    "is_boundary_six": false,
    "is_dot": false
  },
  {
    "over": 7,
    "ball": 4,
    "batsman": "Salt",
    "non_striker": "",
    "bowler": "Noor Ahmad",
    "runs_off_bat": 6,
    "extras": 0,
    "extra_type": null,
    "wicket": false,
    "wicket_type": null,
    "fielder": null,
    "commentary_text": "Googly tossed up into the slot outside off. Salt gets down on one knee early and clobbers it over deep mid wicket!",
    "cumulative_score": 74,
    "cumulative_wickets": 1,
    "is_boundary_four": false,
    "is_boundary_six": true,
    "is_dot": false
  },
  {
    "over": 7,
    "ball": 5,
    "batsman": "Salt",
    "non_striker": "",
    "bowler": "Noor Ahmad",
    "runs_off_bat": 1,
    "extras": 0,
    "extra_type": null,
    "wicket": false,
    "wicket_type": null,
    "fielder": null,
    "commentary_text": "shorter outside off. Salt waits on it before cutting it towards sweeper cover",
    "cumulative_score": 75,
    "cumulative_wickets": 1,
    "is_boundary_four": false,
    "is_boundary_six": false,
    "is_dot": false
  },
  {
    "over": 7,
    "ball": 6,
    "batsman": "Padikkal",
    "non_striker": "",
    "bowler": "Noor Ahmad",
    "runs_off_bat": 1,
    "extras": 0,
    "extra_type": null,
    "wicket": false,
    "wicket_type": null,
    "fielder": null,
    "commentary_text": "darted in on a length on middle and leg. Padikkal tucks it off his pads towards deep backward square leg",
    "cumulative_score": 76,
    "cumulative_wickets": 1,
    "is_boundary_four": false,
    "is_boundary_six": false,
    "is_dot": false
  },
  {
    "over": 8,
    "ball": 1,
    "batsman": "Padikkal",
    "non_striker": "",
    "bowler": "Overton",
    "runs_off_bat": 1,
    "extras": 0,
    "extra_type": null,
    "wicket": false,
    "wicket_type": null,
    "fielder": null,
    "commentary_text": "short on leg. Padikkal looks for the pull but is a tad rushed on it. Cloths it towards deep backward square leg",
    "cumulative_score": 77,
    "cumulative_wickets": 1,
    "is_boundary_four": false,
    "is_boundary_six": false,
    "is_dot": false
  },
  {
    "over": 8,
    "ball": 2,
    "batsman": "Salt",
    "non_striker": "",
    "bowler": "Overton",
    "runs_off_bat": 2,
    "extras": 0,
    "extra_type": null,
    "wicket": false,
    "wicket_type": null,
    "fielder": null,
    "commentary_text": "full and wide outside off. Salt moves across his stumps and drills it towards mid off, who dives to his left and gets something behind it. Mhatre the fielder",
    "cumulative_score": 79,
    "cumulative_wickets": 1,
    "is_boundary_four": false,
    "is_boundary_six": false,
    "is_dot": false
  },
  {
    "over": 8,
    "ball": 3,
    "batsman": "Salt",
    "non_striker": "",
    "bowler": "Overton",
    "runs_off_bat": 1,
    "extras": 0,
    "extra_type": null,
    "wicket": false,
    "wicket_type": null,
    "fielder": null,
    "commentary_text": "short and wide outside off. Salt reaches out for it and slaps it towards sweeper cover",
    "cumulative_score": 80,
    "cumulative_wickets": 1,
    "is_boundary_four": false,
    "is_boundary_six": false,
    "is_dot": false
  },
  {
    "over": 8,
    "ball": 4,
    "batsman": "Padikkal",
    "non_striker": "",
    "bowler": "Overton",
    "runs_off_bat": 2,
    "extras": 0,
    "extra_type": null,
    "wicket": false,
    "wicket_type": null,
    "fielder": null,
    "commentary_text": "length outside off. Padikkal comes forward and chips it over extra cover. Back for another brace",
    "cumulative_score": 82,
    "cumulative_wickets": 1,
    "is_boundary_four": false,
    "is_boundary_six": false,
    "is_dot": false
  },
  {
    "over": 8,
    "ball": 5,
    "batsman": "Padikkal",
    "non_striker": "",
    "bowler": "Overton",
    "runs_off_bat": 4,
    "extras": 0,
    "extra_type": null,
    "wicket": false,
    "wicket_type": null,
    "fielder": null,
    "commentary_text": "Length ball on middle and leg. Padikkal pre-empts the line, walks across his stumps and helps it over short fine leg!",
    "cumulative_score": 86,
    "cumulative_wickets": 1,
    "is_boundary_four": true,
    "is_boundary_six": false,
    "is_dot": false
  },
  {
    "over": 8,
    "ball": 6,
    "batsman": "Padikkal",
    "non_striker": "",
    "bowler": "Overton",
    "runs_off_bat": 1,
    "extras": 0,
    "extra_type": null,
    "wicket": false,
    "wicket_type": null,
    "fielder": null,
    "commentary_text": "fuller just outside off. Padikkal has a big swing at it and slices it down to deep third. Keeps strike too",
    "cumulative_score": 87,
    "cumulative_wickets": 1,
    "is_boundary_four": false,
    "is_boundary_six": false,
    "is_dot": false
  },
  {
    "over": 9,
    "ball": 1,
    "batsman": "Padikkal",
    "non_striker": "",
    "bowler": "Noor Ahmad",
    "runs_off_bat": 0,
    "extras": 0,
    "extra_type": null,
    "wicket": false,
    "wicket_type": null,
    "fielder": null,
    "commentary_text": "angled in full on middle and off. Padikkal tips it to extra cover and sets off for a single, only to be sent back by his partner. Sent back in time, though",
    "cumulative_score": 87,
    "cumulative_wickets": 1,
    "is_boundary_four": false,
    "is_boundary_six": false,
    "is_dot": true
  },
  {
    "over": 9,
    "ball": 2,
    "batsman": "Padikkal",
    "non_striker": "",
    "bowler": "Noor Ahmad",
    "runs_off_bat": 0,
    "extras": 0,
    "extra_type": null,
    "wicket": false,
    "wicket_type": null,
    "fielder": null,
    "commentary_text": "leg-spinner on a length on off. Padikkal backs away before prodding it towards extra cover. Wants the single again but Salt is not as interested",
    "cumulative_score": 87,
    "cumulative_wickets": 1,
    "is_boundary_four": false,
    "is_boundary_six": false,
    "is_dot": true
  },
  {
    "over": 9,
    "ball": 3,
    "batsman": "Padikkal",
    "non_striker": "",
    "bowler": "Noor Ahmad",
    "runs_off_bat": 0,
    "extras": 0,
    "extra_type": null,
    "wicket": false,
    "wicket_type": null,
    "fielder": null,
    "commentary_text": "back of a length outside off and this fizzes through. Padikkal shapes for the cut but is beaten by the extra skid",
    "cumulative_score": 87,
    "cumulative_wickets": 1,
    "is_boundary_four": false,
    "is_boundary_six": false,
    "is_dot": true
  },
  {
    "over": 9,
    "ball": 4,
    "batsman": "Padikkal",
    "non_striker": "",
    "bowler": "Noor Ahmad",
    "runs_off_bat": 1,
    "extras": 0,
    "extra_type": null,
    "wicket": false,
    "wicket_type": null,
    "fielder": null,
    "commentary_text": "back of a length on middle and leg. Padikkal tucks it off his pads towards deep backward square leg",
    "cumulative_score": 88,
    "cumulative_wickets": 1,
    "is_boundary_four": false,
    "is_boundary_six": false,
    "is_dot": false
  },
  {
    "over": 9,
    "ball": 5,
    "batsman": "Salt",
    "non_striker": "",
    "bowler": "Noor Ahmad",
    "runs_off_bat": 1,
    "extras": 0,
    "extra_type": null,
    "wicket": false,
    "wicket_type": null,
    "fielder": null,
    "commentary_text": "length ball on the pads. Salt hangs back and works it towards deep mid wicket",
    "cumulative_score": 89,
    "cumulative_wickets": 1,
    "is_boundary_four": false,
    "is_boundary_six": false,
    "is_dot": false
  },
  {
    "over": 9,
    "ball": 6,
    "batsman": "Padikkal",
    "non_striker": "",
    "bowler": "Noor Ahmad",
    "runs_off_bat": 2,
    "extras": 0,
    "extra_type": null,
    "wicket": false,
    "wicket_type": null,
    "fielder": null,
    "commentary_text": "fired in full just down leg. Padikkal brings out the sweep and nudges it past short fine. Kamboj gives chase and keeps it to two",
    "cumulative_score": 91,
    "cumulative_wickets": 1,
    "is_boundary_four": false,
    "is_boundary_six": false,
    "is_dot": false
  },
  {
    "over": 10,
    "ball": 1,
    "batsman": "Salt",
    "non_striker": "",
    "bowler": "Dube",
    "runs_off_bat": 0,
    "extras": 0,
    "extra_type": null,
    "wicket": false,
    "wicket_type": null,
    "fielder": null,
    "commentary_text": "slow, short and wide outside off. Salt jumps up onto his toes and tugs it towards extra cover",
    "cumulative_score": 91,
    "cumulative_wickets": 1,
    "is_boundary_four": false,
    "is_boundary_six": false,
    "is_dot": true
  },
  {
    "over": 10,
    "ball": 2,
    "batsman": "Salt",
    "non_striker": "",
    "bowler": "Dube",
    "runs_off_bat": 1,
    "extras": 0,
    "extra_type": null,
    "wicket": false,
    "wicket_type": null,
    "fielder": null,
    "commentary_text": "well, this is almost a wide but on the other side. Full toss sliding down leg and Salt somehow chalks it behind square towards short fine. He will feel he missed out",
    "cumulative_score": 92,
    "cumulative_wickets": 1,
    "is_boundary_four": false,
    "is_boundary_six": false,
    "is_dot": false
  },
  {
    "over": 10,
    "ball": 3,
    "batsman": "Padikkal",
    "non_striker": "",
    "bowler": "Dube",
    "runs_off_bat": 1,
    "extras": 0,
    "extra_type": null,
    "wicket": false,
    "wicket_type": null,
    "fielder": null,
    "commentary_text": "back of a length outside off. Padikkal goes back and across before tapping it towards backward point",
    "cumulative_score": 93,
    "cumulative_wickets": 1,
    "is_boundary_four": false,
    "is_boundary_six": false,
    "is_dot": false
  },
  {
    "over": 10,
    "ball": 4,
    "batsman": "Salt",
    "non_striker": "",
    "bowler": "Dube",
    "runs_off_bat": 0,
    "extras": 0,
    "extra_type": null,
    "wicket": true,
    "wicket_type": "other",
    "fielder": null,
    "commentary_text": "Dube does the trick! Inspired bowling change, and Salt perishes! This is banged into the track outside off. Seems like the slower variant and it comes off very sluggishly. Salt has a wild swipe at it and shanks it a mile up. Noor runs in from deep square and snaffles up the chance. Timely breakthrough for CSK!",
    "cumulative_score": 93,
    "cumulative_wickets": 2,
    "is_boundary_four": false,
    "is_boundary_six": false,
    "is_dot": false
  },
  {
    "over": 10,
    "ball": 5,
    "batsman": "Patidar",
    "non_striker": "",
    "bowler": "Dube",
    "runs_off_bat": 1,
    "extras": 0,
    "extra_type": null,
    "wicket": false,
    "wicket_type": null,
    "fielder": null,
    "commentary_text": "back of a length just outside off. Patidar gets up on his toes and pats it to long on to open his account",
    "cumulative_score": 94,
    "cumulative_wickets": 2,
    "is_boundary_four": false,
    "is_boundary_six": false,
    "is_dot": false
  },
  {
    "over": 10,
    "ball": 6,
    "batsman": "Padikkal",
    "non_striker": "",
    "bowler": "Dube",
    "runs_off_bat": 4,
    "extras": 0,
    "extra_type": null,
    "wicket": false,
    "wicket_type": null,
    "fielder": null,
    "commentary_text": "Not the greatest ball Dube will ever bowl. Too much width on offer and Padikkal slashes it over short third!",
    "cumulative_score": 98,
    "cumulative_wickets": 2,
    "is_boundary_four": true,
    "is_boundary_six": false,
    "is_dot": false
  },
  {
    "over": 11,
    "ball": 1,
    "batsman": "Patidar",
    "non_striker": "",
    "bowler": "Noor Ahmad",
    "runs_off_bat": 6,
    "extras": 0,
    "extra_type": null,
    "wicket": false,
    "wicket_type": null,
    "fielder": null,
    "commentary_text": "Floated up full outside off. Patidar comes forward and takes on the long boundary, creaming it over sweeper cover!",
    "cumulative_score": 104,
    "cumulative_wickets": 2,
    "is_boundary_four": false,
    "is_boundary_six": true,
    "is_dot": false
  },
  {
    "over": 11,
    "ball": 2,
    "batsman": "Patidar",
    "non_striker": "",
    "bowler": "Noor Ahmad",
    "runs_off_bat": 1,
    "extras": 0,
    "extra_type": null,
    "wicket": false,
    "wicket_type": null,
    "fielder": null,
    "commentary_text": "fired in on a length on middle and off. Patidar drops it into the off side and picks up a run",
    "cumulative_score": 105,
    "cumulative_wickets": 2,
    "is_boundary_four": false,
    "is_boundary_six": false,
    "is_dot": false
  },
  {
    "over": 11,
    "ball": 3,
    "batsman": "Padikkal",
    "non_striker": "",
    "bowler": "Noor Ahmad",
    "runs_off_bat": 6,
    "extras": 0,
    "extra_type": null,
    "wicket": false,
    "wicket_type": null,
    "fielder": null,
    "commentary_text": "oh, send an airplane to fetch that back! Given a bit of air on middle and leg. Padikkal dances down the track and launches it a mile over long on!",
    "cumulative_score": 111,
    "cumulative_wickets": 2,
    "is_boundary_four": false,
    "is_boundary_six": true,
    "is_dot": false
  },
  {
    "over": 11,
    "ball": 4,
    "batsman": "Padikkal",
    "non_striker": "",
    "bowler": "Noor Ahmad",
    "runs_off_bat": 0,
    "extras": 1,
    "extra_type": "legbye",
    "wicket": false,
    "wicket_type": null,
    "fielder": null,
    "commentary_text": "googly on a length on middle and leg. Spins in and beats Padikkal on the inside. Rolls off the back leg towards short third",
    "cumulative_score": 112,
    "cumulative_wickets": 2,
    "is_boundary_four": false,
    "is_boundary_six": false,
    "is_dot": false
  },
  {
    "over": 11,
    "ball": 5,
    "batsman": "Patidar",
    "non_striker": "",
    "bowler": "Noor Ahmad",
    "runs_off_bat": 1,
    "extras": 0,
    "extra_type": null,
    "wicket": false,
    "wicket_type": null,
    "fielder": null,
    "commentary_text": "googly on a full length on middle. Patidar pushes it to long off",
    "cumulative_score": 113,
    "cumulative_wickets": 2,
    "is_boundary_four": false,
    "is_boundary_six": false,
    "is_dot": false
  },
  {
    "over": 11,
    "ball": 6,
    "batsman": "Padikkal",
    "non_striker": "",
    "bowler": "Noor Ahmad",
    "runs_off_bat": 1,
    "extras": 0,
    "extra_type": null,
    "wicket": false,
    "wicket_type": null,
    "fielder": null,
    "commentary_text": "back of a length outside off. Padikkal stays back and cuts it towards deep backward point",
    "cumulative_score": 114,
    "cumulative_wickets": 2,
    "is_boundary_four": false,
    "is_boundary_six": false,
    "is_dot": false
  },
  {
    "over": 12,
    "ball": 1,
    "batsman": "Padikkal",
    "non_striker": "",
    "bowler": "Dube",
    "runs_off_bat": 1,
    "extras": 0,
    "extra_type": null,
    "wicket": false,
    "wicket_type": null,
    "fielder": null,
    "commentary_text": "back of a length outside off. Padikkal gets on top of the bounce and punches it towards sweeper cover",
    "cumulative_score": 115,
    "cumulative_wickets": 2,
    "is_boundary_four": false,
    "is_boundary_six": false,
    "is_dot": false
  },
  {
    "over": 12,
    "ball": 1,
    "batsman": "Padikkal",
    "non_striker": "",
    "bowler": "Dube",
    "runs_off_bat": 0,
    "extras": 1,
    "extra_type": "wide",
    "wicket": false,
    "wicket_type": null,
    "fielder": null,
    "commentary_text": "length ball hung up wide outside off. Padikkal lets it go and sees the umpire indulge in some exercise",
    "cumulative_score": 116,
    "cumulative_wickets": 2,
    "is_boundary_four": false,
    "is_boundary_six": false,
    "is_dot": false
  },
  {
    "over": 12,
    "ball": 2,
    "batsman": "Patidar",
    "non_striker": "",
    "bowler": "Dube",
    "runs_off_bat": 6,
    "extras": 0,
    "extra_type": null,
    "wicket": false,
    "wicket_type": null,
    "fielder": null,
    "commentary_text": "Banged half-way down and this gets up to near the helmet. Patidar rushed on it and he miscues it off the bottom half of the way. Gets just enough to clear a leaping Noor at deep backward square leg!",
    "cumulative_score": 122,
    "cumulative_wickets": 2,
    "is_boundary_four": false,
    "is_boundary_six": true,
    "is_dot": false
  },
  {
    "over": 12,
    "ball": 3,
    "batsman": "Patidar",
    "non_striker": "",
    "bowler": "Dube",
    "runs_off_bat": 1,
    "extras": 0,
    "extra_type": null,
    "wicket": false,
    "wicket_type": null,
    "fielder": null,
    "commentary_text": "length ball on middle and leg. Eased out to deep mid wicket",
    "cumulative_score": 123,
    "cumulative_wickets": 2,
    "is_boundary_four": false,
    "is_boundary_six": false,
    "is_dot": false
  },
  {
    "over": 12,
    "ball": 4,
    "batsman": "Padikkal",
    "non_striker": "",
    "bowler": "Dube",
    "runs_off_bat": 6,
    "extras": 0,
    "extra_type": null,
    "wicket": false,
    "wicket_type": null,
    "fielder": null,
    "commentary_text": "This is a slower ball and this lands right in the slot outside off. Padikkal hares down the track and smokes it over wide long off!",
    "cumulative_score": 129,
    "cumulative_wickets": 2,
    "is_boundary_four": false,
    "is_boundary_six": true,
    "is_dot": false
  },
  {
    "over": 12,
    "ball": 5,
    "batsman": "Padikkal",
    "non_striker": "",
    "bowler": "Dube",
    "runs_off_bat": 4,
    "extras": 0,
    "extra_type": null,
    "wicket": false,
    "wicket_type": null,
    "fielder": null,
    "commentary_text": "four more! Dube being torn apart this over! Padikkal knows this is going to be wide, and that it is going to be shortish too. He goes back and across before gliding it past backward point!",
    "cumulative_score": 133,
    "cumulative_wickets": 2,
    "is_boundary_four": true,
    "is_boundary_six": false,
    "is_dot": false
  },
  {
    "over": 12,
    "ball": 6,
    "batsman": "Padikkal",
    "non_striker": "",
    "bowler": "Dube",
    "runs_off_bat": 4,
    "extras": 0,
    "extra_type": null,
    "wicket": false,
    "wicket_type": null,
    "fielder": null,
    "commentary_text": "Right in the slot just outside off. Padikkal loads up, gets his front foot out of the way and bludgeons it back past the bowler!",
    "cumulative_score": 137,
    "cumulative_wickets": 2,
    "is_boundary_four": true,
    "is_boundary_six": false,
    "is_dot": false
  },
  {
    "over": 13,
    "ball": 1,
    "batsman": "Patidar",
    "non_striker": "",
    "bowler": "Henry",
    "runs_off_bat": 6,
    "extras": 0,
    "extra_type": null,
    "wicket": false,
    "wicket_type": null,
    "fielder": null,
    "commentary_text": "This is effortless batting. Slot ball outside off. Patidar goes through the line and just bunts it over mid off!",
    "cumulative_score": 143,
    "cumulative_wickets": 2,
    "is_boundary_four": false,
    "is_boundary_six": true,
    "is_dot": false
  },
  {
    "over": 13,
    "ball": 2,
    "batsman": "Patidar",
    "non_striker": "",
    "bowler": "Henry",
    "runs_off_bat": 1,
    "extras": 0,
    "extra_type": null,
    "wicket": false,
    "wicket_type": null,
    "fielder": null,
    "commentary_text": "slower bumper on off. Patidar hangs back before hacking it to deep mid wicket",
    "cumulative_score": 144,
    "cumulative_wickets": 2,
    "is_boundary_four": false,
    "is_boundary_six": false,
    "is_dot": false
  },
  {
    "over": 13,
    "ball": 3,
    "batsman": "Padikkal",
    "non_striker": "",
    "bowler": "Henry",
    "runs_off_bat": 2,
    "extras": 0,
    "extra_type": null,
    "wicket": false,
    "wicket_type": null,
    "fielder": null,
    "commentary_text": "Back of a length outside off. Padikkal reaches out for it and slaps it flat towards extra cover. Gaikwad lunges to to his right but cannot make a tough chance stick!",
    "cumulative_score": 146,
    "cumulative_wickets": 2,
    "is_boundary_four": false,
    "is_boundary_six": false,
    "is_dot": false
  },
  {
    "over": 13,
    "ball": 4,
    "batsman": "Padikkal",
    "non_striker": "",
    "bowler": "Henry",
    "runs_off_bat": 0,
    "extras": 0,
    "extra_type": null,
    "wicket": false,
    "wicket_type": null,
    "fielder": null,
    "commentary_text": "dug into the track on leg. Padikkal gets under it and the square leg umpire calls it a wide on height. But hang on. CSK have reviewed it. And Ball Tracking reckons the ball is 0.01m under the head. Wide call overturned",
    "cumulative_score": 146,
    "cumulative_wickets": 2,
    "is_boundary_four": false,
    "is_boundary_six": false,
    "is_dot": true
  },
  {
    "over": 13,
    "ball": 5,
    "batsman": "Padikkal",
    "non_striker": "",
    "bowler": "Henry",
    "runs_off_bat": 4,
    "extras": 0,
    "extra_type": null,
    "wicket": false,
    "wicket_type": null,
    "fielder": null,
    "commentary_text": "short, wide and this is too easy! Padikkal has the freedom of the Chinnaswamy to work with and he thunders it over extra cover!",
    "cumulative_score": 150,
    "cumulative_wickets": 2,
    "is_boundary_four": true,
    "is_boundary_six": false,
    "is_dot": false
  },
  {
    "over": 13,
    "ball": 6,
    "batsman": "Padikkal",
    "non_striker": "",
    "bowler": "Henry",
    "runs_off_bat": 1,
    "extras": 0,
    "extra_type": null,
    "wicket": false,
    "wicket_type": null,
    "fielder": null,
    "commentary_text": "another short ball outside off. Rushes onto Padikkal and he cloths his pull to long on. , though - and this has been an amazing knock after a tricky teething period!",
    "cumulative_score": 151,
    "cumulative_wickets": 2,
    "is_boundary_four": false,
    "is_boundary_six": false,
    "is_dot": false
  },
  {
    "over": 14,
    "ball": 1,
    "batsman": "Padikkal",
    "non_striker": "",
    "bowler": "Overton",
    "runs_off_bat": 0,
    "extras": 0,
    "extra_type": null,
    "wicket": true,
    "wicket_type": "other",
    "fielder": null,
    "commentary_text": "leg stump out of the ground, and Overton provides a bit of respite to CSK! Yorker speared in on leg stump. Padikkal walks across and tries to be too funky. Looks for the scoop but gets across far too much to access the ball. Misses it and sees his leg stump flat on the ground soon after. Overton is pumped, but Padikkal has done his job too through these middle overs!",
    "cumulative_score": 151,
    "cumulative_wickets": 3,
    "is_boundary_four": false,
    "is_boundary_six": false,
    "is_dot": false
  },
  {
    "over": 14,
    "ball": 2,
    "batsman": "David",
    "non_striker": "",
    "bowler": "Overton",
    "runs_off_bat": 0,
    "extras": 0,
    "extra_type": null,
    "wicket": false,
    "wicket_type": null,
    "fielder": null,
    "commentary_text": "zipped in full on middle and leg. David plays with the angle and tucks it to mid wicket",
    "cumulative_score": 151,
    "cumulative_wickets": 3,
    "is_boundary_four": false,
    "is_boundary_six": false,
    "is_dot": true
  },
  {
    "over": 14,
    "ball": 3,
    "batsman": "David",
    "non_striker": "",
    "bowler": "Overton",
    "runs_off_bat": 0,
    "extras": 0,
    "extra_type": null,
    "wicket": false,
    "wicket_type": null,
    "fielder": null,
    "commentary_text": "Back of a length in the channel and this skips through. Bowled at 148.6kph and David, swishing at it, is beaten for pace",
    "cumulative_score": 151,
    "cumulative_wickets": 3,
    "is_boundary_four": false,
    "is_boundary_six": false,
    "is_dot": true
  },
  {
    "over": 14,
    "ball": 4,
    "batsman": "David",
    "non_striker": "",
    "bowler": "Overton",
    "runs_off_bat": 0,
    "extras": 0,
    "extra_type": null,
    "wicket": false,
    "wicket_type": null,
    "fielder": null,
    "commentary_text": "slanted in full on the stumps. David pokes it back to the bowler, who gets his boot in the way. That was bowled at 145.4kph",
    "cumulative_score": 151,
    "cumulative_wickets": 3,
    "is_boundary_four": false,
    "is_boundary_six": false,
    "is_dot": true
  },
  {
    "over": 14,
    "ball": 5,
    "batsman": "David",
    "non_striker": "",
    "bowler": "Overton",
    "runs_off_bat": 1,
    "extras": 0,
    "extra_type": null,
    "wicket": false,
    "wicket_type": null,
    "fielder": null,
    "commentary_text": "length ball hung up wide outside off. David throws his hands at it and flays it on the bounce to sweeper cover",
    "cumulative_score": 152,
    "cumulative_wickets": 3,
    "is_boundary_four": false,
    "is_boundary_six": false,
    "is_dot": false
  },
  {
    "over": 14,
    "ball": 6,
    "batsman": "Patidar",
    "non_striker": "",
    "bowler": "Overton",
    "runs_off_bat": 0,
    "extras": 1,
    "extra_type": "legbye",
    "wicket": false,
    "wicket_type": null,
    "fielder": null,
    "commentary_text": "off-pace on a back of a length on off. Patidar too early into the pull and the ball bobbles off the back thigh behind point",
    "cumulative_score": 153,
    "cumulative_wickets": 3,
    "is_boundary_four": false,
    "is_boundary_six": false,
    "is_dot": false
  },
  {
    "over": 15,
    "ball": 1,
    "batsman": "Patidar",
    "non_striker": "",
    "bowler": "Khaleel Ahmed",
    "runs_off_bat": 1,
    "extras": 0,
    "extra_type": null,
    "wicket": false,
    "wicket_type": null,
    "fielder": null,
    "commentary_text": "hard length on the stumps. Patidar gives himself room and punches it uppishly towards sweeper cover",
    "cumulative_score": 154,
    "cumulative_wickets": 3,
    "is_boundary_four": false,
    "is_boundary_six": false,
    "is_dot": false
  },
  {
    "over": 15,
    "ball": 2,
    "batsman": "David",
    "non_striker": "",
    "bowler": "Khaleel Ahmed",
    "runs_off_bat": 1,
    "extras": 0,
    "extra_type": null,
    "wicket": false,
    "wicket_type": null,
    "fielder": null,
    "commentary_text": "shortish outside off. David winds up and hoicks it towards deep backward square leg",
    "cumulative_score": 155,
    "cumulative_wickets": 3,
    "is_boundary_four": false,
    "is_boundary_six": false,
    "is_dot": false
  },
  {
    "over": 15,
    "ball": 3,
    "batsman": "Patidar",
    "non_striker": "",
    "bowler": "Khaleel Ahmed",
    "runs_off_bat": 6,
    "extras": 0,
    "extra_type": null,
    "wicket": false,
    "wicket_type": null,
    "fielder": null,
    "commentary_text": "Low full toss outside off. Patidar peels the outer cover off the ball and carves it over extra cover!",
    "cumulative_score": 161,
    "cumulative_wickets": 3,
    "is_boundary_four": false,
    "is_boundary_six": true,
    "is_dot": false
  },
  {
    "over": 15,
    "ball": 3,
    "batsman": "Patidar",
    "non_striker": "",
    "bowler": "Khaleel Ahmed",
    "runs_off_bat": 0,
    "extras": 1,
    "extra_type": "wide",
    "wicket": false,
    "wicket_type": null,
    "fielder": null,
    "commentary_text": "slower bumper outside off. Patidar tries to force it through the off side but only swishes at thin air. Patidar asks his partner whether it is worth the review, and This could be touch-and-go. Had a bit of a loopy trajectory. Ball Tracking comes up.",
    "cumulative_score": 162,
    "cumulative_wickets": 3,
    "is_boundary_four": false,
    "is_boundary_six": false,
    "is_dot": false
  },
  {
    "over": 15,
    "ball": 4,
    "batsman": "Patidar",
    "non_striker": "",
    "bowler": "Khaleel Ahmed",
    "runs_off_bat": 0,
    "extras": 0,
    "extra_type": null,
    "wicket": false,
    "wicket_type": null,
    "fielder": null,
    "commentary_text": "big, big lbw shout but not given! CSK review now! Excellent yorker, zoning into off stump. Patidar has a swing across the line and seems to miss, with the ball later kissing the back leg. Was he struck outside off and was it going beyond the stumps with the angle? Well, nothing doing on either of those counts because",
    "cumulative_score": 162,
    "cumulative_wickets": 3,
    "is_boundary_four": false,
    "is_boundary_six": false,
    "is_dot": true
  },
  {
    "over": 15,
    "ball": 5,
    "batsman": "Patidar",
    "non_striker": "",
    "bowler": "Khaleel Ahmed",
    "runs_off_bat": 4,
    "extras": 0,
    "extra_type": null,
    "wicket": false,
    "wicket_type": null,
    "fielder": null,
    "commentary_text": "Slower ball on a back of a length outside off. Patidar holds his swing and then slices it over backward point!",
    "cumulative_score": 166,
    "cumulative_wickets": 3,
    "is_boundary_four": true,
    "is_boundary_six": false,
    "is_dot": false
  },
  {
    "over": 15,
    "ball": 6,
    "batsman": "Patidar",
    "non_striker": "",
    "bowler": "Khaleel Ahmed",
    "runs_off_bat": 6,
    "extras": 0,
    "extra_type": null,
    "wicket": false,
    "wicket_type": null,
    "fielder": null,
    "commentary_text": "Khaleel dishes out another length ball into Patidar's wheelhouse, and he gets met. Patidar gets his front foot out of the way and wallops it over deep mid wicket!",
    "cumulative_score": 172,
    "cumulative_wickets": 3,
    "is_boundary_four": false,
    "is_boundary_six": true,
    "is_dot": false
  },
  {
    "over": 16,
    "ball": 1,
    "batsman": "David",
    "non_striker": "",
    "bowler": "Noor Ahmad",
    "runs_off_bat": 1,
    "extras": 0,
    "extra_type": null,
    "wicket": false,
    "wicket_type": null,
    "fielder": null,
    "commentary_text": "leg-spinner on a full length on middle and leg. David comes forward and drives it towards deep extra cover",
    "cumulative_score": 173,
    "cumulative_wickets": 3,
    "is_boundary_four": false,
    "is_boundary_six": false,
    "is_dot": false
  },
  {
    "over": 16,
    "ball": 2,
    "batsman": "Patidar",
    "non_striker": "",
    "bowler": "Noor Ahmad",
    "runs_off_bat": 0,
    "extras": 1,
    "extra_type": "bye",
    "wicket": false,
    "wicket_type": null,
    "fielder": null,
    "commentary_text": "back of a length just outside off. Patidar shapes for the reverse and misses. Samson fumbles too and RCB pinch a bye",
    "cumulative_score": 174,
    "cumulative_wickets": 3,
    "is_boundary_four": false,
    "is_boundary_six": false,
    "is_dot": false
  },
  {
    "over": 16,
    "ball": 3,
    "batsman": "David",
    "non_striker": "",
    "bowler": "Noor Ahmad",
    "runs_off_bat": 6,
    "extras": 0,
    "extra_type": null,
    "wicket": false,
    "wicket_type": null,
    "fielder": null,
    "commentary_text": "Googly dropped short outside off. David sits deep in his crease and forehands it over long off!",
    "cumulative_score": 180,
    "cumulative_wickets": 3,
    "is_boundary_four": false,
    "is_boundary_six": true,
    "is_dot": false
  },
  {
    "over": 16,
    "ball": 4,
    "batsman": "David",
    "non_striker": "",
    "bowler": "Noor Ahmad",
    "runs_off_bat": 6,
    "extras": 0,
    "extra_type": null,
    "wicket": false,
    "wicket_type": null,
    "fielder": null,
    "commentary_text": "David's party has well and truly begun now! This is another feeble attempt at a hard length delivery. Sits up on middle and leg and David dismisses it over deep mid wicket!",
    "cumulative_score": 186,
    "cumulative_wickets": 3,
    "is_boundary_four": false,
    "is_boundary_six": true,
    "is_dot": false
  },
  {
    "over": 16,
    "ball": 5,
    "batsman": "David",
    "non_striker": "",
    "bowler": "Noor Ahmad",
    "runs_off_bat": 6,
    "extras": 0,
    "extra_type": null,
    "wicket": false,
    "wicket_type": null,
    "fielder": null,
    "commentary_text": "David is on a rampage now, and this crowd is loving it! Another half-tracker outside off. David has all the time in the world to line it up and slap it over deep cover!",
    "cumulative_score": 192,
    "cumulative_wickets": 3,
    "is_boundary_four": false,
    "is_boundary_six": true,
    "is_dot": false
  },
  {
    "over": 16,
    "ball": 6,
    "batsman": "David",
    "non_striker": "",
    "bowler": "Noor Ahmad",
    "runs_off_bat": 1,
    "extras": 0,
    "extra_type": null,
    "wicket": false,
    "wicket_type": null,
    "fielder": null,
    "commentary_text": "shortish just outside off. David hangs back and jabs it towards sweeper cover",
    "cumulative_score": 193,
    "cumulative_wickets": 3,
    "is_boundary_four": false,
    "is_boundary_six": false,
    "is_dot": false
  },
  {
    "over": 17,
    "ball": 1,
    "batsman": "David",
    "non_striker": "",
    "bowler": "Kamboj",
    "runs_off_bat": 4,
    "extras": 0,
    "extra_type": null,
    "wicket": false,
    "wicket_type": null,
    "fielder": null,
    "commentary_text": "Kamboj greeted with a boundary! Low full toss laced with width. David throws the plumbing at it and pummels it past extra cover!",
    "cumulative_score": 197,
    "cumulative_wickets": 3,
    "is_boundary_four": true,
    "is_boundary_six": false,
    "is_dot": false
  },
  {
    "over": 17,
    "ball": 2,
    "batsman": "David",
    "non_striker": "",
    "bowler": "Kamboj",
    "runs_off_bat": 0,
    "extras": 0,
    "extra_type": null,
    "wicket": false,
    "wicket_type": null,
    "fielder": null,
    "commentary_text": "zipped in full on leg stump. Right in the slot and Kamboj is lucky he does not have to fetch this back from Cubbon Park. David misses his swish and gets rapped on the pad. David livid with himself too",
    "cumulative_score": 197,
    "cumulative_wickets": 3,
    "is_boundary_four": false,
    "is_boundary_six": false,
    "is_dot": true
  },
  {
    "over": 17,
    "ball": 3,
    "batsman": "David",
    "non_striker": "",
    "bowler": "Kamboj",
    "runs_off_bat": 2,
    "extras": 0,
    "extra_type": null,
    "wicket": false,
    "wicket_type": null,
    "fielder": null,
    "commentary_text": "into the blockhole outside off. David cannot get under it and squeezes it past extra cover for a couple of runs",
    "cumulative_score": 199,
    "cumulative_wickets": 3,
    "is_boundary_four": false,
    "is_boundary_six": false,
    "is_dot": false
  },
  {
    "over": 17,
    "ball": 4,
    "batsman": "David",
    "non_striker": "",
    "bowler": "Kamboj",
    "runs_off_bat": 0,
    "extras": 0,
    "extra_type": null,
    "wicket": false,
    "wicket_type": null,
    "fielder": null,
    "commentary_text": "finally nails the wide yorker. David swings at it with all his might and misses. But hang on, he thinks this should be a wide. Did not seem so in real-time but why not have a look. David has walked a shade across his stumps and the ball is well inside the tramlines. RCB lose a review!",
    "cumulative_score": 199,
    "cumulative_wickets": 3,
    "is_boundary_four": false,
    "is_boundary_six": false,
    "is_dot": true
  },
  {
    "over": 17,
    "ball": 5,
    "batsman": "David",
    "non_striker": "",
    "bowler": "Kamboj",
    "runs_off_bat": 6,
    "extras": 0,
    "extra_type": null,
    "wicket": false,
    "wicket_type": null,
    "fielder": null,
    "commentary_text": "full toss on a Free hit and of course David takes full toll! Proper buffet ball outside off and David helps himself to a thump over mid on!",
    "cumulative_score": 205,
    "cumulative_wickets": 3,
    "is_boundary_four": false,
    "is_boundary_six": true,
    "is_dot": false
  },
  {
    "over": 17,
    "ball": 5,
    "batsman": "David",
    "non_striker": "",
    "bowler": "Kamboj",
    "runs_off_bat": 0,
    "extras": 1,
    "extra_type": "no_ball",
    "wicket": false,
    "wicket_type": null,
    "fielder": null,
    "commentary_text": "Kamboj outwits David, and the stumps have been shattered again! Searing yorker on leg. David pre-empts another wide delivery and walks across his stumps. Too far to then make contact and his leg stump is pegged back. But there is a reprieve for David because",
    "cumulative_score": 206,
    "cumulative_wickets": 3,
    "is_boundary_four": false,
    "is_boundary_six": false,
    "is_dot": false
  },
  {
    "over": 17,
    "ball": 6,
    "batsman": "David",
    "non_striker": "",
    "bowler": "Kamboj",
    "runs_off_bat": 1,
    "extras": 0,
    "extra_type": null,
    "wicket": false,
    "wicket_type": null,
    "fielder": null,
    "commentary_text": "into the blockhole outside off. David cannot get under this and scuffs it out to long off",
    "cumulative_score": 207,
    "cumulative_wickets": 3,
    "is_boundary_four": false,
    "is_boundary_six": false,
    "is_dot": false
  },
  {
    "over": 18,
    "ball": 1,
    "batsman": "David",
    "non_striker": "",
    "bowler": "Overton",
    "runs_off_bat": 6,
    "extras": 0,
    "extra_type": null,
    "wicket": false,
    "wicket_type": null,
    "fielder": null,
    "commentary_text": "Slot ball outside leg. David can pick his spot and he plunders it over the long leg fence!",
    "cumulative_score": 213,
    "cumulative_wickets": 3,
    "is_boundary_four": false,
    "is_boundary_six": true,
    "is_dot": false
  },
  {
    "over": 18,
    "ball": 2,
    "batsman": "David",
    "non_striker": "",
    "bowler": "Overton",
    "runs_off_bat": 2,
    "extras": 0,
    "extra_type": null,
    "wicket": false,
    "wicket_type": null,
    "fielder": null,
    "commentary_text": "low full toss outside off. David has a wild swipe at it and squirts it off the inside edge past short fine leg. Back for a brace",
    "cumulative_score": 215,
    "cumulative_wickets": 3,
    "is_boundary_four": false,
    "is_boundary_six": false,
    "is_dot": false
  },
  {
    "over": 18,
    "ball": 3,
    "batsman": "David",
    "non_striker": "",
    "bowler": "Overton",
    "runs_off_bat": 4,
    "extras": 0,
    "extra_type": null,
    "wicket": false,
    "wicket_type": null,
    "fielder": null,
    "commentary_text": "when it is going your way, it all goes your way! Banged in short just outside off. David rushed on the pull and the ball flies off the top edge over the keeper!",
    "cumulative_score": 219,
    "cumulative_wickets": 3,
    "is_boundary_four": true,
    "is_boundary_six": false,
    "is_dot": false
  },
  {
    "over": 18,
    "ball": 4,
    "batsman": "David",
    "non_striker": "",
    "bowler": "Overton",
    "runs_off_bat": 6,
    "extras": 0,
    "extra_type": null,
    "wicket": false,
    "wicket_type": null,
    "fielder": null,
    "commentary_text": "a 21-ball fifty for Tim David, and the Chinnaswamy erupts! A lot of RCB fans will end up with sore throats tonight, if David keeps this going. Full outside off and David pumps it over mid on!",
    "cumulative_score": 225,
    "cumulative_wickets": 3,
    "is_boundary_four": false,
    "is_boundary_six": true,
    "is_dot": false
  },
  {
    "over": 18,
    "ball": 5,
    "batsman": "David",
    "non_striker": "",
    "bowler": "Overton",
    "runs_off_bat": 6,
    "extras": 0,
    "extra_type": null,
    "wicket": false,
    "wicket_type": null,
    "fielder": null,
    "commentary_text": "the sixes keep getting bigger and bigger! Right in the slot outside off. David winds up and clobbers the living daylights out of this. Clean over the sightscreen!",
    "cumulative_score": 231,
    "cumulative_wickets": 3,
    "is_boundary_four": false,
    "is_boundary_six": true,
    "is_dot": false
  },
  {
    "over": 18,
    "ball": 6,
    "batsman": "David",
    "non_striker": "",
    "bowler": "Overton",
    "runs_off_bat": 6,
    "extras": 0,
    "extra_type": null,
    "wicket": false,
    "wicket_type": null,
    "fielder": null,
    "commentary_text": "onto the roof, and onto the metro station! Or somewhere in the near vicinity! Half-way down outside off. David rubs his eyes in disbelief before clattering it an absolute mile over deep mid wicket!",
    "cumulative_score": 237,
    "cumulative_wickets": 3,
    "is_boundary_four": false,
    "is_boundary_six": true,
    "is_dot": false
  },
  {
    "over": 19,
    "ball": 1,
    "batsman": "Patidar",
    "non_striker": "",
    "bowler": "Kamboj",
    "runs_off_bat": 6,
    "extras": 0,
    "extra_type": null,
    "wicket": false,
    "wicket_type": null,
    "fielder": null,
    "commentary_text": "full, wide and into the stands it flies! This is like a video game now. Too much width on offer and Patidar scythes it over deep point!",
    "cumulative_score": 243,
    "cumulative_wickets": 3,
    "is_boundary_four": false,
    "is_boundary_six": true,
    "is_dot": false
  },
  {
    "over": 19,
    "ball": 2,
    "batsman": "Patidar",
    "non_striker": "",
    "bowler": "Kamboj",
    "runs_off_bat": 0,
    "extras": 0,
    "extra_type": null,
    "wicket": false,
    "wicket_type": null,
    "fielder": null,
    "commentary_text": "high full toss outside off. Patidar tries to hit it too hard and shanks it back to the bowler",
    "cumulative_score": 243,
    "cumulative_wickets": 3,
    "is_boundary_four": false,
    "is_boundary_six": false,
    "is_dot": true
  },
  {
    "over": 19,
    "ball": 3,
    "batsman": "Patidar",
    "non_striker": "",
    "bowler": "Kamboj",
    "runs_off_bat": 1,
    "extras": 0,
    "extra_type": null,
    "wicket": false,
    "wicket_type": null,
    "fielder": null,
    "commentary_text": "top yorker outside off. Patidar jams down on it and digs it out towards deep point",
    "cumulative_score": 244,
    "cumulative_wickets": 3,
    "is_boundary_four": false,
    "is_boundary_six": false,
    "is_dot": false
  },
  {
    "over": 19,
    "ball": 4,
    "batsman": "David",
    "non_striker": "",
    "bowler": "Kamboj",
    "runs_off_bat": 1,
    "extras": 0,
    "extra_type": null,
    "wicket": false,
    "wicket_type": null,
    "fielder": null,
    "commentary_text": "full and wide. David throws his hands at it and drills it out towards sweeper cover",
    "cumulative_score": 245,
    "cumulative_wickets": 3,
    "is_boundary_four": false,
    "is_boundary_six": false,
    "is_dot": false
  },
  {
    "over": 19,
    "ball": 5,
    "batsman": "Patidar",
    "non_striker": "",
    "bowler": "Kamboj",
    "runs_off_bat": 1,
    "extras": 0,
    "extra_type": null,
    "wicket": false,
    "wicket_type": null,
    "fielder": null,
    "commentary_text": "another top wide yorker. Patidar cannot do much with it apart from clinking it off the toe-end towards sweeper cover",
    "cumulative_score": 246,
    "cumulative_wickets": 3,
    "is_boundary_four": false,
    "is_boundary_six": false,
    "is_dot": false
  },
  {
    "over": 19,
    "ball": 6,
    "batsman": "David",
    "non_striker": "",
    "bowler": "Kamboj",
    "runs_off_bat": 4,
    "extras": 0,
    "extra_type": null,
    "wicket": false,
    "wicket_type": null,
    "fielder": null,
    "commentary_text": "Sarfaraz loses it in the lights, and David has turbocharged RCB to 250! Full on the pads. David walks down the track and flicks it to deep mid wicket. Sarfaraz does not know where the ball is, and it bobbles past him and into the fence!",
    "cumulative_score": 250,
    "cumulative_wickets": 3,
    "is_boundary_four": true,
    "is_boundary_six": false,
    "is_dot": false
  }
]